Workbook

Sheet Ventas_Original
A1: ID_Transaccion | B1: Fecha | C1: Sucursal | D1: Vendedor | E1: Categoria | F1: Producto | G1: Cantidad | H1: Precio_Unitario | I1: Costo_Unitario
A2: TRX-1001 | B2: 46027 | C2: Corrientes | D2: Juan Perez | E2: Alimentos | F2: Yerba Mate 1kg | G2: 15 | H2: 3500 | I2: 2400
A3: TRX-1002 | B3: 46028 | C3: Resistencia | D3: Maria Gomez | E3: Tecnologia | F3: Auriculares Bluetooth | G3: 4 | H3: 25000 | I3: 16000
A4: TRX-1003 | B4: 46028 | C4: Corrientes | D4: juan perez | E4: Alimentos | F4: Yerba Mate 1kg | G4: 8 | H4: 3500 | I4: 2400
A5: TRX-1004 | B5: 46030 | C5: Posadas | D5: Carlos Ruiz | E5: Accesorios | F5: Correa Canina 3m | G5: 12 | H5: 8500 | I5: 5000
A6: TRX-1005 | B6: 46032 | C6: Corrientes | D6: Maria Gomez | E6: Tecnologia | F6: Soporte Notebook | G6: 3 | H6: 18000 | I6: 11000
A7: TRX-1006 | B7: 46033 | C7: Resistencia | D7: Juan Perez | E7: Alimentos | F7: Alimento Perro 20kg | G7: 5 | H7: 42000 | I7: 30000
A8: TRX-1007 | B8: 46034 | C8: Posadas | D8: Carlos Ruiz | E8: Alimentos | F8: Yerba Mate 1kg | G8: 20 | H8: 3500 | I8: 2400
A9: TRX-1008 | B9: 46037 | C9: Corrientes | D9: Maria Gomez | E9: Accesorios | F9: Juguete Mordillo | G9: 15 | H9: 4500 | I9: 2500
A10: TRX-1009 | B10: 46038 | C10: Resistencia | D10: Juan Perez | E10: Tecnologia | F10: Auriculares Bluetooth | G10: 6 | H10: 25000 | I10: 16000
A11: TRX-1010 | B11: 46040 | C11: Corrientes | D11: Carlos Ruiz | E11: Alimentos | F11: Alimento Gato 10kg | G11: 10 | H11: 28000 | I11: 19000
A12: TRX-1011 | B12: 46042 | C12: Posadas | D12: Maria Gomez | E12: Alimentos | F12: Yerba Mate 1kg | G12: 14 | H12: 3500 | I12: 2400
A13: TRX-1012 | B13: 46044 | C13: Resistencia | D13: Carlos Ruiz | E13: Accesorios | F13: Correa Canina 3m | G13: 9 | H13: 8500 | I13: 5000
... A21: TRX-1020 | B21: 46065 | C21: Corrientes | D21: Carlos Ruiz | E21: Tecnologia | F21: Soporte Notebook | G21: 5 | H21: 18000 | I21: 11000

Sheet Modulo_1_Resolucion
A1: ID_Transaccion | B1: Fecha | C1: Sucursal | D1: Vendedor | E1: Categoria | F1: Producto | G1: Cantidad | H1: Precio_Unitario | I1: Costo_Unitario | J1: Sucursal_Limpia | K1: Vendedor_Limpio | L1: Control_ID | M1: Codigo_Region | N1: Total_Venta | O1: Total_Costo | P1: Ganancia_Neta | Q1: Proveedor | R1: Categoria_Oficial | S1: Comision_Estado | T1: Cantidad Auditada
A2: TRX-1001 | B2: 46027 | C2: Corrientes | D2: Juan Perez | E2: Alimentos | F2: Yerba Mate 1kg | G2: 15 | H2: 3500 | I2: 2400 | J2: =TRIM(C2) -> Corrientes | K2: =PROPER(TRIM(D2)) -> Juan Perez | L2: =LEN(A2) -> 8 | M2: =LEFT(A2, 2) -> TR | N2: =G2*H2 -> 52500 | O2: =G2*I2 -> 36000 | P2: =N2-O2 -> 16500 | Q2: {=IFERROR(_xlfn.XLOOKUP(F2, Maestro_Productos_Precios!$B:$B, Maestro_Productos_Precios!$D:$D), "No Encontrado")} -> Cooperativa Neike | R2: {=IFERROR(INDEX(Maestro_Productos_Precios!$C:$C, MATCH(F2, Maestro_Productos_Precios!$B:$B, 0)), "Producto No Sincronizado")} -> Alimentos | S2: =IFS(AND(N2>50000, J2="Corrientes"), N2*0.05, TRUE, N2*0.02) -> 2625 | T2: =IF(G2<=0,1,G2) -> 15
A3: TRX-1002 | B3: 46028 | C3: Resistencia | D3: Maria Gomez | E3: Tecnologia | F3: Auriculares Bluetooth | G3: 4 | H3: 25000 | I3: 16000 | J3: =TRIM(C3) -> Resistencia | K3: =PROPER(TRIM(D3)) -> Maria Gomez | L3: =LEN(A3) -> 8 | M3: =LEFT(A3, 2) -> TR | N3: =G3*H3 -> 100000 | O3: =G3*I3 -> 64000 | P3: =N3-O3 -> 36000 | Q3: {=IFERROR(_xlfn.XLOOKUP(F3, Maestro_Productos_Precios!$B:$B, Maestro_Productos_Precios!$D:$D), "No Encontrado")} -> TechImport S.R.L. | R3: {=IFERROR(INDEX(Maestro_Productos_Precios!$C:$C, MATCH(F3, Maestro_Productos_Precios!$B:$B, 0)), "Producto No Sincronizado")} -> Tecnologia | S3: =IFS(AND(N3>50000, J3="Corrientes"), N3*0.05, TRUE, N3*0.02) -> 2000 | T3: =IF(G3<=0,1,G3) -> 4
A4: TRX-1003 | B4: 46028 | C4: Corrientes | D4: juan perez | E4: Alimentos | F4: Yerba Mate 1kg | G4: 8 | H4: 3500 | I4: 2400 | J4: =TRIM(C4) -> Corrientes | K4: =PROPER(TRIM(D4)) -> Juan Perez | L4: =LEN(A4) -> 8 | M4: =LEFT(A4, 2) -> TR | N4: =G4*H4 -> 28000 | O4: =G4*I4 -> 19200 | P4: =N4-O4 -> 8800 | Q4: {=IFERROR(_xlfn.XLOOKUP(F4, Maestro_Productos_Precios!$B:$B, Maestro_Productos_Precios!$D:$D), "No Encontrado")} -> Cooperativa Neike | R4: {=IFERROR(INDEX(Maestro_Productos_Precios!$C:$C, MATCH(F4, Maestro_Productos_Precios!$B:$B, 0)), "Producto No Sincronizado")} -> Alimentos | S4: =IFS(AND(N4>50000, J4="Corrientes"), N4*0.05, TRUE, N4*0.02) -> 560 | T4: =IF(G4<=0,1,G4) -> 8
A5: TRX-1004 | B5: 46030 | C5: Posadas | D5: Carlos Ruiz | E5: Accesorios | F5: Correa Canina 3m | G5: 12 | H5: 8500 | I5: 5000 | J5: =TRIM(C5) -> Posadas | K5: =PROPER(TRIM(D5)) -> Carlos Ruiz | L5: =LEN(A5) -> 8 | M5: =LEFT(A5, 2) -> TR | N5: =G5*H5 -> 102000 | O5: =G5*I5 -> 60000 | P5: =N5-O5 -> 42000 | Q5: {=IFERROR(_xlfn.XLOOKUP(F5, Maestro_Productos_Precios!$B:$B, Maestro_Productos_Precios!$D:$D), "No Encontrado")} -> PetStyle Litoral | R5: {=IFERROR(INDEX(Maestro_Productos_Precios!$C:$C, MATCH(F5, Maestro_Productos_Precios!$B:$B, 0)), "Producto No Sincronizado")} -> Accesorios | S5: =IFS(AND(N5>50000, J5="Corrientes"), N5*0.05, TRUE, N5*0.02) -> 2040 | T5: =IF(G5<=0,1,G5) -> 12
A6: TRX-1005 | B6: 46032 | C6: Corrientes | D6: Maria Gomez | E6: Tecnologia | F6: Soporte Notebook | G6: 3 | H6: 18000 | I6: 11000 | J6: =TRIM(C6) -> Corrientes | K6: =PROPER(TRIM(D6)) -> Maria Gomez | L6: =LEN(A6) -> 8 | M6: =LEFT(A6, 2) -> TR | N6: =G6*H6 -> 54000 | O6: =G6*I6 -> 33000 | P6: =N6-O6 -> 21000 | Q6: {=IFERROR(_xlfn.XLOOKUP(F6, Maestro_Productos_Precios!$B:$B, Maestro_Productos_Precios!$D:$D), "No Encontrado")} -> TechImport S.R.L. | R6: {=IFERROR(INDEX(Maestro_Productos_Precios!$C:$C, MATCH(F6, Maestro_Productos_Precios!$B:$B, 0)), "Producto No Sincronizado")} -> Tecnologia | S6: =IFS(AND(N6>50000, J6="Corrientes"), N6*0.05, TRUE, N6*0.02) -> 2700 | T6: =IF(G6<=0,1,G6) -> 3
A7: TRX-1006 | B7: 46033 | C7: Resistencia | D7: Juan Perez | E7: Alimentos | F7: Alimento Perro 20kg | G7: 5 | H7: 42000 | I7: 30000 | J7: =TRIM(C7) -> Resistencia | K7: =PROPER(TRIM(D7)) -> Juan Perez | L7: =LEN(A7) -> 8 | M7: =LEFT(A7, 2) -> TR | N7: =G7*H7 -> 210000 | O7: =G7*I7 -> 150000 | P7: =N7-O7 -> 60000 | Q7: {=IFERROR(_xlfn.XLOOKUP(F7, Maestro_Productos_Precios!$B:$B, Maestro_Productos_Precios!$D:$D), "No Encontrado")} -> NutriDog Arg | R7: {=IFERROR(INDEX(Maestro_Productos_Precios!$C:$C, MATCH(F7, Maestro_Productos_Precios!$B:$B, 0)), "Producto No Sincronizado")} -> Alimentos | S7: =IFS(AND(N7>50000, J7="Corrientes"), N7*0.05, TRUE, N7*0.02) -> 4200 | T7: =IF(G7<=0,1,G7) -> 5
A8: TRX-1007 | B8: 46034 | C8: Posadas | D8: Carlos Ruiz | E8: Alimentos | F8: Yerba Mate 1kg | G8: 20 | H8: 3500 | I8: 2400 | J8: =TRIM(C8) -> Posadas | K8: =PROPER(TRIM(D8)) -> Carlos Ruiz | L8: =LEN(A8) -> 8 | M8: =LEFT(A8, 2) -> TR | N8: =G8*H8 -> 70000 | O8: =G8*I8 -> 48000 | P8: =N8-O8 -> 22000 | Q8: {=IFERROR(_xlfn.XLOOKUP(F8, Maestro_Productos_Precios!$B:$B, Maestro_Productos_Precios!$D:$D), "No Encontrado")} -> Cooperativa Neike | R8: {=IFERROR(INDEX(Maestro_Productos_Precios!$C:$C, MATCH(F8, Maestro_Productos_Precios!$B:$B, 0)), "Producto No Sincronizado")} -> Alimentos | S8: =IFS(AND(N8>50000, J8="Corrientes"), N8*0.05, TRUE, N8*0.02) -> 1400 | T8: =IF(G8<=0,1,G8) -> 20
A9: TRX-1008 | B9: 46037 | C9: Corrientes | D9: Maria Gomez | E9: Accesorios | F9: Juguete Mordillo | G9: 15 | H9: 4500 | I9: 2500 | J9: =TRIM(C9) -> Corrientes | K9: =PROPER(TRIM(D9)) -> Maria Gomez | L9: =LEN(A9) -> 8 | M9: =LEFT(A9, 2) -> TR | N9: =G9*H9 -> 67500 | O9: =G9*I9 -> 37500 | P9: =N9-O9 -> 30000 | Q9: {=IFERROR(_xlfn.XLOOKUP(F9, Maestro_Productos_Precios!$B:$B, Maestro_Productos_Precios!$D:$D), "No Encontrado")} -> PetStyle Litoral | R9: {=IFERROR(INDEX(Maestro_Productos_Precios!$C:$C, MATCH(F9, Maestro_Productos_Precios!$B:$B, 0)), "Producto No Sincronizado")} -> Accesorios | S9: =IFS(AND(N9>50000, J9="Corrientes"), N9*0.05, TRUE, N9*0.02) -> 3375 | T9: =IF(G9<=0,1,G9) -> 15
A10: TRX-1009 | B10: 46038 | C10: Resistencia | D10: Juan Perez | E10: Tecnologia | F10: Auriculares Bluetooth | G10: 6 | H10: 25000 | I10: 16000 | J10: =TRIM(C10) -> Resistencia | K10: =PROPER(TRIM(D10)) -> Juan Perez | L10: =LEN(A10) -> 8 | M10: =LEFT(A10, 2) -> TR | N10: =G10*H10 -> 150000 | O10: =G10*I10 -> 96000 | P10: =N10-O10 -> 54000 | Q10: {=IFERROR(_xlfn.XLOOKUP(F10, Maestro_Productos_Precios!$B:$B, Maestro_Productos_Precios!$D:$D), "No Encontrado")} -> TechImport S.R.L. | R10: {=IFERROR(INDEX(Maestro_Productos_Precios!$C:$C, MATCH(F10, Maestro_Productos_Precios!$B:$B, 0)), "Producto No Sincronizado")} -> Tecnologia | S10: =IFS(AND(N10>50000, J10="Corrientes"), N10*0.05, TRUE, N10*0.02) -> 3000 | T10: =IF(G10<=0,1,G10) -> 6
A11: TRX-1010 | B11: 46040 | C11: Corrientes | D11: Carlos Ruiz | E11: Alimentos | F11: Alimento Gato 10kg | G11: 10 | H11: 28000 | I11: 19000 | J11: =TRIM(C11) -> Corrientes | K11: =PROPER(TRIM(D11)) -> Carlos Ruiz | L11: =LEN(A11) -> 8 | M11: =LEFT(A11, 2) -> TR | N11: =G11*H11 -> 280000 | O11: =G11*I11 -> 190000 | P11: =N11-O11 -> 90000 | Q11: {=IFERROR(_xlfn.XLOOKUP(F11, Maestro_Productos_Precios!$B:$B, Maestro_Productos_Precios!$D:$D), "No Encontrado")} -> NutriDog Arg | R11: {=IFERROR(INDEX(Maestro_Productos_Precios!$C:$C, MATCH(F11, Maestro_Productos_Precios!$B:$B, 0)), "Producto No Sincronizado")} -> Alimentos | S11: =IFS(AND(N11>50000, J11="Corrientes"), N11*0.05, TRUE, N11*0.02) -> 14000 | T11: =IF(G11<=0,1,G11) -> 10
A12: TRX-1011 | B12: 46042 | C12: Posadas | D12: Maria Gomez | E12: Alimentos | F12: Yerba Mate 1kg | G12: 14 | H12: 3500 | I12: 2400 | J12: =TRIM(C12) -> Posadas | K12: =PROPER(TRIM(D12)) -> Maria Gomez | L12: =LEN(A12) -> 8 | M12: =LEFT(A12, 2) -> TR | N12: =G12*H12 -> 49000 | O12: =G12*I12 -> 33600 | P12: =N12-O12 -> 15400 | Q12: {=IFERROR(_xlfn.XLOOKUP(F12, Maestro_Productos_Precios!$B:$B, Maestro_Productos_Precios!$D:$D), "No Encontrado")} -> Cooperativa Neike | R12: {=IFERROR(INDEX(Maestro_Productos_Precios!$C:$C, MATCH(F12, Maestro_Productos_Precios!$B:$B, 0)), "Producto No Sincronizado")} -> Alimentos | S12: =IFS(AND(N12>50000, J12="Corrientes"), N12*0.05, TRUE, N12*0.02) -> 980 | T12: =IF(G12<=0,1,G12) -> 14
A13: TRX-1012 | B13: 46044 | C13: Resistencia | D13: Carlos Ruiz | E13: Accesorios | F13: Correa Canina 3m | G13: 9 | H13: 8500 | I13: 5000 | J13: =TRIM(C13) -> Resistencia | K13: =PROPER(TRIM(D13)) -> Carlos Ruiz | L13: =LEN(A13) -> 8 | M13: =LEFT(A13, 2) -> TR | N13: =G13*H13 -> 76500 | O13: =G13*I13 -> 45000 | P13: =N13-O13 -> 31500 | Q13: {=IFERROR(_xlfn.XLOOKUP(F13, Maestro_Productos_Precios!$B:$B, Maestro_Productos_Precios!$D:$D), "No Encontrado")} -> PetStyle Litoral | R13: {=IFERROR(INDEX(Maestro_Productos_Precios!$C:$C, MATCH(F13, Maestro_Productos_Precios!$B:$B, 0)), "Producto No Sincronizado")} -> Accesorios | S13: =IFS(AND(N13>50000, J13="Corrientes"), N13*0.05, TRUE, N13*0.02) -> 1530 | T13: =IF(G13<=0,1,G13) -> 9
... A21: TRX-1020 | B21: 46065 | C21: Corrientes | D21: Carlos Ruiz | E21: Tecnologia | F21: Soporte Notebook | G21: 5 | H21: 18000 | I21: 11000 | J21: =TRIM(C21) -> Corrientes | K21: =PROPER(TRIM(D21)) -> Carlos Ruiz | L21: =LEN(A21) -> 8 | M21: =LEFT(A21, 2) -> TR | N21: =G21*H21 -> 90000 | O21: =G21*I21 -> 55000 | P21: =N21-O21 -> 35000 | Q21: {=IFERROR(_xlfn.XLOOKUP(F21, Maestro_Productos_Precios!$B:$B, Maestro_Productos_Precios!$D:$D), "No Encontrado")} -> TechImport S.R.L. | R21: {=IFERROR(INDEX(Maestro_Productos_Precios!$C:$C, MATCH(F21, Maestro_Productos_Precios!$B:$B, 0)), "Producto No Sincronizado")} -> Tecnologia | S21: =IFS(AND(N21>50000, J21="Corrientes"), N21*0.05, TRUE, N21*0.02) -> 4500 | T21: =IF(G21<=0,1,G21) -> 5

Sheet Maestro_Productos_Precios
A1: SKU | B1: Producto | C1: Categoria | D1: Proveedor | E1: Precio_Lista | F1: Costo_Base | G1: Margen_Esperado
A2: SKU-501 | B2: Yerba Mate 1kg | C2: Alimentos | D2: Cooperativa Neike | E2: 3500 | F2: 2400 | G2: 0.31
A3: SKU-502 | B3: Auriculares Bluetooth | C3: Tecnologia | D3: TechImport S.R.L. | E3: 25000 | F3: 16000 | G3: 0.36
A4: SKU-503 | B4: Correa Canina 3m | C4: Accesorios | D4: PetStyle Litoral | E4: 8500 | F4: 5000 | G4: 0.41
A5: SKU-504 | B5: Soporte Notebook | C5: Tecnologia | D5: TechImport S.R.L. | E5: 18000 | F5: 11000 | G5: 0.38
A6: SKU-505 | B6: Alimento Perro 20kg | C6: Alimentos | D6: NutriDog Arg | E6: 42000 | F6: 30000 | G6: 0.28
A7: SKU-506 | B7: Juguete Mordillo | C7: Accesorios | D7: PetStyle Litoral | E7: 4500 | F7: 2500 | G7: 0.44
A8: SKU-507 | B8: Alimento Gato 10kg | C8: Alimentos | D8: NutriDog Arg | E8: 28000 | F8: 19000 | G8: 0.32

Sheet Reporte_Consolidado_M1
A1: Sucursal | B1: Total_Ventas
A2: Corrientes | B2: {=SUM( IFS(Modulo_1_Resolucion!$J$2:$J$21=A2, Modulo_1_Resolucion!$G$2:$G$21*Modulo_1_Resolucion!$H$2:$H$21, TRUE, 0))} -> 875500
A3: Resistencia | B3: {=SUM(IFS(Modulo_1_Resolucion!$J$2:$J$21=A3, Modulo_1_Resolucion!$G$2:$G$21*Modulo_1_Resolucion!$H$2:$H$21, TRUE, 0))} -> 799500
A4: Posadas | B4: {=SUM( IFS(Modulo_1_Resolucion!$J$2:$J$21=A4, Modulo_1_Resolucion!$G$2:$G$21*Modulo_1_Resolucion!$H$2:$H$21, TRUE, 0))} -> 725000
A5: Formosa | B5: {=SUM(IFS(Modulo_1_Resolucion!$J$2:$J$21=A5, Modulo_1_Resolucion!$G$2:$G$21*Modulo_1_Resolucion!$H$2:$H$21, TRUE, 0))} -> 0

Sheet Dashboard_Ejecutivo
A1: Facturación Total General | B1: =SUM(Modulo_1_Resolucion!N2:N21) -> 2400000 | D1: Valor a 3 meses de Facturación | E1: $3.500.000,00 | M1: =IFERROR(__xludf.DUMMYFUNCTION("QUERY(Modulo_1_Resolucion!E1:N21, ""SELECT E, SUM(N) WHERE E IS NOT NULL GROUP BY E"", 1)"),"Categoria") -> Categoria | N1: =IFERROR(__xludf.DUMMYFUNCTION("""COMPUTED_VALUE"""),"sum Total_Venta") -> sum Total_Venta
A2: Ticket Promedio por Operación | B2: =AVERAGE(Modulo_1_Resolucion!N2:N21) -> 120000 | M2: =IFERROR(__xludf.DUMMYFUNCTION("""COMPUTED_VALUE"""),"Accesorios") -> Accesorios | N2: =IFERROR(__xludf.DUMMYFUNCTION("""COMPUTED_VALUE"""),336000.0) -> 336000
A3: Margen Promedio General | B3: =AVERAGE(Modulo_1_Resolucion!P2:P21)/AVERAGE(Modulo_1_Resolucion!N2:N21) -> 0.344375 | M3: =IFERROR(__xludf.DUMMYFUNCTION("""COMPUTED_VALUE"""),"Alimentos") -> Alimentos | N3: =IFERROR(__xludf.DUMMYFUNCTION("""COMPUTED_VALUE"""),1344000.0) -> 1344000
M4: =IFERROR(__xludf.DUMMYFUNCTION("""COMPUTED_VALUE"""),"Tecnologia") -> Tecnologia | N4: =IFERROR(__xludf.DUMMYFUNCTION("""COMPUTED_VALUE"""),720000.0) -> 720000
