Workbook

Sheet ventas_raw_200
A1: ID_Transaccion | B1: Fecha | C1: Sucursal | D1: Vendedor | E1: Producto | F1: Cantidad | G1: Precio_Unitario | H1: Costo_Unitario | I1: Sucursal_limpio | J1: Vendedor_limpio | K1: Producto_limpio | L1: Largo_ID | M1: ID_Transaccion_Limpio | N1: Largo_ID2 | O1: Cantidad_Auditada | P1: Categoria_oficial | Q1: Proveedor_Oficial | R1: Total_Venta | S1: Total_Costo | T1: Ganancia | U1: Comision
A2: TRX-1001 | B2: 46111 | C2: Corrientes | D2: Ana Martinez | E2: mates de madera calada | F2: 8 | G2: 8500 | H2: 4800 | I2: =PROPER(TRIM(ventas_raw_200[[#This Row],[Sucursal]])) -> Corrientes | J2: =PROPER(TRIM(ventas_raw_200[[#This Row],[Vendedor]])) -> Ana Martinez | K2: =PROPER(TRIM(ventas_raw_200[[#This Row],[Producto]])) -> Mates De Madera Calada | L2: =LEN(ventas_raw_200[[#This Row],[ID_Transaccion]]) -> 8 | M2: =TRIM(ventas_raw_200[[#This Row],[ID_Transaccion]]) -> TRX-1001 | N2: =LEN(ventas_raw_200[[#This Row],[ID_Transaccion_Limpio]]) -> 8 | O2: =IFERROR(IF(ventas_raw_200[[#This Row],[Cantidad]]<0,1,ventas_raw_200[[#This Row],[Cantidad]]),1) -> 8 | P2: =IFERROR(_xlfn.XLOOKUP(K2,maestro_productos_15!$B$2:$B$16,maestro_productos_15!$C$2:$C$16),"No encontrada") -> Bazar | Q2: =IFERROR(_xlfn.XLOOKUP(K2,maestro_productos_15!$B$2:$B$16,maestro_productos_15!$D$2:$D$16),"No encontrada") -> Artesanías Guaraníes | R2: =ventas_raw_200[[#This Row],[Precio_Unitario]]*ventas_raw_200[[#This Row],[Cantidad_Auditada]] -> 68000 | S2: =ventas_raw_200[[#This Row],[Costo_Unitario]]*ventas_raw_200[[#This Row],[Cantidad_Auditada]] -> 38400 | T2: =ventas_raw_200[[#This Row],[Total_Venta]]-ventas_raw_200[[#This Row],[Total_Costo]] -> 29600 | U2: {=_xlfn.IFS(AND(G2>25000,I2="Corrientes"),O2*G2*0.06,G2>25000,O2*G2*0.04,TRUE,O2*G2*0.02)} -> 1360
A3: TRX-1002 | B3: 46106 | C3: Posadas | D3: Juan Perez | E3: termo acero inoxidable 1.3l | F3: 2 | G3: 32000 | H3: 21000 | I3: =PROPER(TRIM(ventas_raw_200[[#This Row],[Sucursal]])) -> Posadas | J3: =PROPER(TRIM(ventas_raw_200[[#This Row],[Vendedor]])) -> Juan Perez | K3: =PROPER(TRIM(ventas_raw_200[[#This Row],[Producto]])) -> Termo Acero Inoxidable 1.3L | L3: =LEN(ventas_raw_200[[#This Row],[ID_Transaccion]]) -> 8 | M3: =TRIM(ventas_raw_200[[#This Row],[ID_Transaccion]]) -> TRX-1002 | N3: =LEN(ventas_raw_200[[#This Row],[ID_Transaccion_Limpio]]) -> 8 | O3: =IFERROR(IF(ventas_raw_200[[#This Row],[Cantidad]]<0,1,ventas_raw_200[[#This Row],[Cantidad]]),1) -> 2 | P3: =IFERROR(_xlfn.XLOOKUP(K3,maestro_productos_15!$B$2:$B$16,maestro_productos_15!$C$2:$C$16),"No encontrada") -> Bazar | Q3: =IFERROR(_xlfn.XLOOKUP(K3,maestro_productos_15!$B$2:$B$16,maestro_productos_15!$D$2:$D$16),"No encontrada") -> Distribuidora del Nordeste | R3: =ventas_raw_200[[#This Row],[Precio_Unitario]]*ventas_raw_200[[#This Row],[Cantidad_Auditada]] -> 64000 | S3: =ventas_raw_200[[#This Row],[Costo_Unitario]]*ventas_raw_200[[#This Row],[Cantidad_Auditada]] -> 42000 | T3: =ventas_raw_200[[#This Row],[Total_Venta]]-ventas_raw_200[[#This Row],[Total_Costo]] -> 22000 | U3: {=_xlfn.IFS(AND(G3>25000,I3="Corrientes"),O3*G3*0.06,G3>25000,O3*G3*0.04,TRUE,O3*G3*0.02)} -> 2560
A4: TRX-1003 | B4: 46082 | C4: Posadas | D4: Juan Perez | E4: Mouse Inalámbrico Ergonómico | F4: 23 | G4: 15000 | H4: 9500 | I4: =PROPER(TRIM(ventas_raw_200[[#This Row],[Sucursal]])) -> Posadas | J4: =PROPER(TRIM(ventas_raw_200[[#This Row],[Vendedor]])) -> Juan Perez | K4: =PROPER(TRIM(ventas_raw_200[[#This Row],[Producto]])) -> Mouse Inalámbrico Ergonómico | L4: =LEN(ventas_raw_200[[#This Row],[ID_Transaccion]]) -> 8 | M4: =TRIM(ventas_raw_200[[#This Row],[ID_Transaccion]]) -> TRX-1003 | N4: =LEN(ventas_raw_200[[#This Row],[ID_Transaccion_Limpio]]) -> 8 | O4: =IFERROR(IF(ventas_raw_200[[#This Row],[Cantidad]]<0,1,ventas_raw_200[[#This Row],[Cantidad]]),1) -> 23 | P4: =IFERROR(_xlfn.XLOOKUP(K4,maestro_productos_15!$B$2:$B$16,maestro_productos_15!$C$2:$C$16),"No encontrada") -> Tecnología | Q4: =IFERROR(_xlfn.XLOOKUP(K4,maestro_productos_15!$B$2:$B$16,maestro_productos_15!$D$2:$D$16),"No encontrada") -> TechImport S.R.L. | R4: =ventas_raw_200[[#This Row],[Precio_Unitario]]*ventas_raw_200[[#This Row],[Cantidad_Auditada]] -> 345000 | S4: =ventas_raw_200[[#This Row],[Costo_Unitario]]*ventas_raw_200[[#This Row],[Cantidad_Auditada]] -> 218500 | T4: =ventas_raw_200[[#This Row],[Total_Venta]]-ventas_raw_200[[#This Row],[Total_Costo]] -> 126500 | U4: {=_xlfn.IFS(AND(G4>25000,I4="Corrientes"),O4*G4*0.06,G4>25000,O4*G4*0.04,TRUE,O4*G4*0.02)} -> 6900
A5: TRX-1004 | B5: 46107 | C5: Resistencia | D5: ANA MARTINEZ | E5: Yerba Mate Premium 1kg | F5: 25 | G5: 3800 | H5: 2500 | I5: =PROPER(TRIM(ventas_raw_200[[#This Row],[Sucursal]])) -> Resistencia | J5: =PROPER(TRIM(ventas_raw_200[[#This Row],[Vendedor]])) -> Ana Martinez | K5: =PROPER(TRIM(ventas_raw_200[[#This Row],[Producto]])) -> Yerba Mate Premium 1Kg | L5: =LEN(ventas_raw_200[[#This Row],[ID_Transaccion]]) -> 8 | M5: =TRIM(ventas_raw_200[[#This Row],[ID_Transaccion]]) -> TRX-1004 | N5: =LEN(ventas_raw_200[[#This Row],[ID_Transaccion_Limpio]]) -> 8 | O5: =IFERROR(IF(ventas_raw_200[[#This Row],[Cantidad]]<0,1,ventas_raw_200[[#This Row],[Cantidad]]),1) -> 25 | P5: =IFERROR(_xlfn.XLOOKUP(K5,maestro_productos_15!$B$2:$B$16,maestro_productos_15!$C$2:$C$16),"No encontrada") -> Alimentos | Q5: =IFERROR(_xlfn.XLOOKUP(K5,maestro_productos_15!$B$2:$B$16,maestro_productos_15!$D$2:$D$16),"No encontrada") -> Cooperativa Neike | R5: =ventas_raw_200[[#This Row],[Precio_Unitario]]*ventas_raw_200[[#This Row],[Cantidad_Auditada]] -> 95000 | S5: =ventas_raw_200[[#This Row],[Costo_Unitario]]*ventas_raw_200[[#This Row],[Cantidad_Auditada]] -> 62500 | T5: =ventas_raw_200[[#This Row],[Total_Venta]]-ventas_raw_200[[#This Row],[Total_Costo]] -> 32500 | U5: {=_xlfn.IFS(AND(G5>25000,I5="Corrientes"),O5*G5*0.06,G5>25000,O5*G5*0.04,TRUE,O5*G5*0.02)} -> 1900
A6: TRX-1005 | B6: 46102 | C6: CORRIENTES | D6: ANA MARTINEZ | E6: Mouse Inalámbrico Ergonómico | F6: 3 | G6: 15000 | H6: 9500 | I6: =PROPER(TRIM(ventas_raw_200[[#This Row],[Sucursal]])) -> Corrientes | J6: =PROPER(TRIM(ventas_raw_200[[#This Row],[Vendedor]])) -> Ana Martinez | K6: =PROPER(TRIM(ventas_raw_200[[#This Row],[Producto]])) -> Mouse Inalámbrico Ergonómico | L6: =LEN(ventas_raw_200[[#This Row],[ID_Transaccion]]) -> 8 | M6: =TRIM(ventas_raw_200[[#This Row],[ID_Transaccion]]) -> TRX-1005 | N6: =LEN(ventas_raw_200[[#This Row],[ID_Transaccion_Limpio]]) -> 8 | O6: =IFERROR(IF(ventas_raw_200[[#This Row],[Cantidad]]<0,1,ventas_raw_200[[#This Row],[Cantidad]]),1) -> 3 | P6: =IFERROR(_xlfn.XLOOKUP(K6,maestro_productos_15!$B$2:$B$16,maestro_productos_15!$C$2:$C$16),"No encontrada") -> Tecnología | Q6: =IFERROR(_xlfn.XLOOKUP(K6,maestro_productos_15!$B$2:$B$16,maestro_productos_15!$D$2:$D$16),"No encontrada") -> TechImport S.R.L. | R6: =ventas_raw_200[[#This Row],[Precio_Unitario]]*ventas_raw_200[[#This Row],[Cantidad_Auditada]] -> 45000 | S6: =ventas_raw_200[[#This Row],[Costo_Unitario]]*ventas_raw_200[[#This Row],[Cantidad_Auditada]] -> 28500 | T6: =ventas_raw_200[[#This Row],[Total_Venta]]-ventas_raw_200[[#This Row],[Total_Costo]] -> 16500 | U6: {=_xlfn.IFS(AND(G6>25000,I6="Corrientes"),O6*G6*0.06,G6>25000,O6*G6*0.04,TRUE,O6*G6*0.02)} -> 900
A7: TRX-1006 | B7: 46051 | C7: Formosa | D7: Juan Perez | E7: correa reforzada canina 3m | F7: 18 | G7: 9200 | H7: 5500 | I7: =PROPER(TRIM(ventas_raw_200[[#This Row],[Sucursal]])) -> Formosa | J7: =PROPER(TRIM(ventas_raw_200[[#This Row],[Vendedor]])) -> Juan Perez | K7: =PROPER(TRIM(ventas_raw_200[[#This Row],[Producto]])) -> Correa Reforzada Canina 3M | L7: =LEN(ventas_raw_200[[#This Row],[ID_Transaccion]]) -> 8 | M7: =TRIM(ventas_raw_200[[#This Row],[ID_Transaccion]]) -> TRX-1006 | N7: =LEN(ventas_raw_200[[#This Row],[ID_Transaccion_Limpio]]) -> 8 | O7: =IFERROR(IF(ventas_raw_200[[#This Row],[Cantidad]]<0,1,ventas_raw_200[[#This Row],[Cantidad]]),1) -> 18 | P7: =IFERROR(_xlfn.XLOOKUP(K7,maestro_productos_15!$B$2:$B$16,maestro_productos_15!$C$2:$C$16),"No encontrada") -> Mascotas | Q7: =IFERROR(_xlfn.XLOOKUP(K7,maestro_productos_15!$B$2:$B$16,maestro_productos_15!$D$2:$D$16),"No encontrada") -> PetStyle Litoral | R7: =ventas_raw_200[[#This Row],[Precio_Unitario]]*ventas_raw_200[[#This Row],[Cantidad_Auditada]] -> 165600 | S7: =ventas_raw_200[[#This Row],[Costo_Unitario]]*ventas_raw_200[[#This Row],[Cantidad_Auditada]] -> 99000 | T7: =ventas_raw_200[[#This Row],[Total_Venta]]-ventas_raw_200[[#This Row],[Total_Costo]] -> 66600 | U7: {=_xlfn.IFS(AND(G7>25000,I7="Corrientes"),O7*G7*0.06,G7>25000,O7*G7*0.04,TRUE,O7*G7*0.02)} -> 3312
A8: TRX-1007 | B8: 46025 | C8: Resistencia | D8: ANA MARTINEZ | E8: Alimento Perro Adulto 15kg | F8: 12 | G8: 35000 | H8: 24000 | I8: =PROPER(TRIM(ventas_raw_200[[#This Row],[Sucursal]])) -> Resistencia | J8: =PROPER(TRIM(ventas_raw_200[[#This Row],[Vendedor]])) -> Ana Martinez | K8: =PROPER(TRIM(ventas_raw_200[[#This Row],[Producto]])) -> Alimento Perro Adulto 15Kg | L8: =LEN(ventas_raw_200[[#This Row],[ID_Transaccion]]) -> 10 | M8: =TRIM(ventas_raw_200[[#This Row],[ID_Transaccion]]) -> TRX-1007 | N8: =LEN(ventas_raw_200[[#This Row],[ID_Transaccion_Limpio]]) -> 8 | O8: =IFERROR(IF(ventas_raw_200[[#This Row],[Cantidad]]<0,1,ventas_raw_200[[#This Row],[Cantidad]]),1) -> 12 | P8: =IFERROR(_xlfn.XLOOKUP(K8,maestro_productos_15!$B$2:$B$16,maestro_productos_15!$C$2:$C$16),"No encontrada") -> Mascotas | Q8: =IFERROR(_xlfn.XLOOKUP(K8,maestro_productos_15!$B$2:$B$16,maestro_productos_15!$D$2:$D$16),"No encontrada") -> NutriDog Arg | R8: =ventas_raw_200[[#This Row],[Precio_Unitario]]*ventas_raw_200[[#This Row],[Cantidad_Auditada]] -> 420000 | S8: =ventas_raw_200[[#This Row],[Costo_Unitario]]*ventas_raw_200[[#This Row],[Cantidad_Auditada]] -> 288000 | T8: =ventas_raw_200[[#This Row],[Total_Venta]]-ventas_raw_200[[#This Row],[Total_Costo]] -> 132000 | U8: {=_xlfn.IFS(AND(G8>25000,I8="Corrientes"),O8*G8*0.06,G8>25000,O8*G8*0.04,TRUE,O8*G8*0.02)} -> 16800
A9: TRX-1008 | B9: 46050 | C9: Formosa | D9: MARIA GOMEZ | E9: Alimento Gato Castrado 10kg | F9: 8 | G9: 29500 | H9: 20000 | I9: =PROPER(TRIM(ventas_raw_200[[#This Row],[Sucursal]])) -> Formosa | J9: =PROPER(TRIM(ventas_raw_200[[#This Row],[Vendedor]])) -> Maria Gomez | K9: =PROPER(TRIM(ventas_raw_200[[#This Row],[Producto]])) -> Alimento Gato Castrado 10Kg | L9: =LEN(ventas_raw_200[[#This Row],[ID_Transaccion]]) -> 8 | M9: =TRIM(ventas_raw_200[[#This Row],[ID_Transaccion]]) -> TRX-1008 | N9: =LEN(ventas_raw_200[[#This Row],[ID_Transaccion_Limpio]]) -> 8 | O9: =IFERROR(IF(ventas_raw_200[[#This Row],[Cantidad]]<0,1,ventas_raw_200[[#This Row],[Cantidad]]),1) -> 8 | P9: =IFERROR(_xlfn.XLOOKUP(K9,maestro_productos_15!$B$2:$B$16,maestro_productos_15!$C$2:$C$16),"No encontrada") -> Mascotas | Q9: =IFERROR(_xlfn.XLOOKUP(K9,maestro_productos_15!$B$2:$B$16,maestro_productos_15!$D$2:$D$16),"No encontrada") -> NutriDog Arg | R9: =ventas_raw_200[[#This Row],[Precio_Unitario]]*ventas_raw_200[[#This Row],[Cantidad_Auditada]] -> 236000 | S9: =ventas_raw_200[[#This Row],[Costo_Unitario]]*ventas_raw_200[[#This Row],[Cantidad_Auditada]] -> 160000 | T9: =ventas_raw_200[[#This Row],[Total_Venta]]-ventas_raw_200[[#This Row],[Total_Costo]] -> 76000 | U9: {=_xlfn.IFS(AND(G9>25000,I9="Corrientes"),O9*G9*0.06,G9>25000,O9*G9*0.04,TRUE,O9*G9*0.02)} -> 9440
A10: TRX-1009 | B10: 46111 | C10: Resistencia | D10: juan perez | E10: Cargador Rápido USB-C 65W | F10: 7 | G10: 22000 | H10: 14000 | I10: =PROPER(TRIM(ventas_raw_200[[#This Row],[Sucursal]])) -> Resistencia | J10: =PROPER(TRIM(ventas_raw_200[[#This Row],[Vendedor]])) -> Juan Perez | K10: =PROPER(TRIM(ventas_raw_200[[#This Row],[Producto]])) -> Cargador Rápido Usb-C 65W | L10: =LEN(ventas_raw_200[[#This Row],[ID_Transaccion]]) -> 8 | M10: =TRIM(ventas_raw_200[[#This Row],[ID_Transaccion]]) -> TRX-1009 | N10: =LEN(ventas_raw_200[[#This Row],[ID_Transaccion_Limpio]]) -> 8 | O10: =IFERROR(IF(ventas_raw_200[[#This Row],[Cantidad]]<0,1,ventas_raw_200[[#This Row],[Cantidad]]),1) -> 7 | P10: =IFERROR(_xlfn.XLOOKUP(K10,maestro_productos_15!$B$2:$B$16,maestro_productos_15!$C$2:$C$16),"No encontrada") -> Tecnología | Q10: =IFERROR(_xlfn.XLOOKUP(K10,maestro_productos_15!$B$2:$B$16,maestro_productos_15!$D$2:$D$16),"No encontrada") -> TechImport S.R.L. | R10: =ventas_raw_200[[#This Row],[Precio_Unitario]]*ventas_raw_200[[#This Row],[Cantidad_Auditada]] -> 154000 | S10: =ventas_raw_200[[#This Row],[Costo_Unitario]]*ventas_raw_200[[#This Row],[Cantidad_Auditada]] -> 98000 | T10: =ventas_raw_200[[#This Row],[Total_Venta]]-ventas_raw_200[[#This Row],[Total_Costo]] -> 56000 | U10: {=_xlfn.IFS(AND(G10>25000,I10="Corrientes"),O10*G10*0.06,G10>25000,O10*G10*0.04,TRUE,O10*G10*0.02)} -> 3080
A11: TRX-1010 | B11: 46076 | C11: Posadas | D11: Ana Martinez | E11: Snack Premios Perro 250g | F11: 24 | G11: 3100 | H11: 1800 | I11: =PROPER(TRIM(ventas_raw_200[[#This Row],[Sucursal]])) -> Posadas | J11: =PROPER(TRIM(ventas_raw_200[[#This Row],[Vendedor]])) -> Ana Martinez | K11: =PROPER(TRIM(ventas_raw_200[[#This Row],[Producto]])) -> Snack Premios Perro 250G | L11: =LEN(ventas_raw_200[[#This Row],[ID_Transaccion]]) -> 8 | M11: =TRIM(ventas_raw_200[[#This Row],[ID_Transaccion]]) -> TRX-1010 | N11: =LEN(ventas_raw_200[[#This Row],[ID_Transaccion_Limpio]]) -> 8 | O11: =IFERROR(IF(ventas_raw_200[[#This Row],[Cantidad]]<0,1,ventas_raw_200[[#This Row],[Cantidad]]),1) -> 24 | P11: =IFERROR(_xlfn.XLOOKUP(K11,maestro_productos_15!$B$2:$B$16,maestro_productos_15!$C$2:$C$16),"No encontrada") -> Mascotas | Q11: =IFERROR(_xlfn.XLOOKUP(K11,maestro_productos_15!$B$2:$B$16,maestro_productos_15!$D$2:$D$16),"No encontrada") -> NutriDog Arg | R11: =ventas_raw_200[[#This Row],[Precio_Unitario]]*ventas_raw_200[[#This Row],[Cantidad_Auditada]] -> 74400 | S11: =ventas_raw_200[[#This Row],[Costo_Unitario]]*ventas_raw_200[[#This Row],[Cantidad_Auditada]] -> 43200 | T11: =ventas_raw_200[[#This Row],[Total_Venta]]-ventas_raw_200[[#This Row],[Total_Costo]] -> 31200 | U11: {=_xlfn.IFS(AND(G11>25000,I11="Corrientes"),O11*G11*0.06,G11>25000,O11*G11*0.04,TRUE,O11*G11*0.02)} -> 1488
A12: TRX-1011 | B12: 46024 | C12: POSADAS | D12: Ana Martinez | E12: Alimento Gato Castrado 10kg | F12: 22 | G12: 29500 | H12: 20000 | I12: =PROPER(TRIM(ventas_raw_200[[#This Row],[Sucursal]])) -> Posadas | J12: =PROPER(TRIM(ventas_raw_200[[#This Row],[Vendedor]])) -> Ana Martinez | K12: =PROPER(TRIM(ventas_raw_200[[#This Row],[Producto]])) -> Alimento Gato Castrado 10Kg | L12: =LEN(ventas_raw_200[[#This Row],[ID_Transaccion]]) -> 8 | M12: =TRIM(ventas_raw_200[[#This Row],[ID_Transaccion]]) -> TRX-1011 | N12: =LEN(ventas_raw_200[[#This Row],[ID_Transaccion_Limpio]]) -> 8 | O12: =IFERROR(IF(ventas_raw_200[[#This Row],[Cantidad]]<0,1,ventas_raw_200[[#This Row],[Cantidad]]),1) -> 22 | P12: =IFERROR(_xlfn.XLOOKUP(K12,maestro_productos_15!$B$2:$B$16,maestro_productos_15!$C$2:$C$16),"No encontrada") -> Mascotas | Q12: =IFERROR(_xlfn.XLOOKUP(K12,maestro_productos_15!$B$2:$B$16,maestro_productos_15!$D$2:$D$16),"No encontrada") -> NutriDog Arg | R12: =ventas_raw_200[[#This Row],[Precio_Unitario]]*ventas_raw_200[[#This Row],[Cantidad_Auditada]] -> 649000 | S12: =ventas_raw_200[[#This Row],[Costo_Unitario]]*ventas_raw_200[[#This Row],[Cantidad_Auditada]] -> 440000 | T12: =ventas_raw_200[[#This Row],[Total_Venta]]-ventas_raw_200[[#This Row],[Total_Costo]] -> 209000 | U12: {=_xlfn.IFS(AND(G12>25000,I12="Corrientes"),O12*G12*0.06,G12>25000,O12*G12*0.04,TRUE,O12*G12*0.02)} -> 25960
A13: TRX-1012 | B13: 46099 | C13: Corrientes | D13: ANA MARTINEZ | E13: termo acero inoxidable 1.3l | F13: 9 | G13: 32000 | H13: 21000 | I13: =PROPER(TRIM(ventas_raw_200[[#This Row],[Sucursal]])) -> Corrientes | J13: =PROPER(TRIM(ventas_raw_200[[#This Row],[Vendedor]])) -> Ana Martinez | K13: =PROPER(TRIM(ventas_raw_200[[#This Row],[Producto]])) -> Termo Acero Inoxidable 1.3L | L13: =LEN(ventas_raw_200[[#This Row],[ID_Transaccion]]) -> 8 | M13: =TRIM(ventas_raw_200[[#This Row],[ID_Transaccion]]) -> TRX-1012 | N13: =LEN(ventas_raw_200[[#This Row],[ID_Transaccion_Limpio]]) -> 8 | O13: =IFERROR(IF(ventas_raw_200[[#This Row],[Cantidad]]<0,1,ventas_raw_200[[#This Row],[Cantidad]]),1) -> 9 | P13: =IFERROR(_xlfn.XLOOKUP(K13,maestro_productos_15!$B$2:$B$16,maestro_productos_15!$C$2:$C$16),"No encontrada") -> Bazar | Q13: =IFERROR(_xlfn.XLOOKUP(K13,maestro_productos_15!$B$2:$B$16,maestro_productos_15!$D$2:$D$16),"No encontrada") -> Distribuidora del Nordeste | R13: =ventas_raw_200[[#This Row],[Precio_Unitario]]*ventas_raw_200[[#This Row],[Cantidad_Auditada]] -> 288000 | S13: =ventas_raw_200[[#This Row],[Costo_Unitario]]*ventas_raw_200[[#This Row],[Cantidad_Auditada]] -> 189000 | T13: =ventas_raw_200[[#This Row],[Total_Venta]]-ventas_raw_200[[#This Row],[Total_Costo]] -> 99000 | U13: {=_xlfn.IFS(AND(G13>25000,I13="Corrientes"),O13*G13*0.06,G13>25000,O13*G13*0.04,TRUE,O13*G13*0.02)} -> 17280
... A201: TRX-1200 | B201: 46075 | C201: Corrientes | D201: Carlos Ruiz | E201: Mates de Madera Calada | F201: 10 | G201: 8500 | H201: 4800 | I201: =PROPER(TRIM(ventas_raw_200[[#This Row],[Sucursal]])) -> Corrientes | J201: =PROPER(TRIM(ventas_raw_200[[#This Row],[Vendedor]])) -> Carlos Ruiz | K201: =PROPER(TRIM(ventas_raw_200[[#This Row],[Producto]])) -> Mates De Madera Calada | L201: =LEN(ventas_raw_200[[#This Row],[ID_Transaccion]]) -> 8 | M201: =TRIM(ventas_raw_200[[#This Row],[ID_Transaccion]]) -> TRX-1200 | N201: =LEN(ventas_raw_200[[#This Row],[ID_Transaccion_Limpio]]) -> 8 | O201: =IFERROR(IF(ventas_raw_200[[#This Row],[Cantidad]]<0,1,ventas_raw_200[[#This Row],[Cantidad]]),1) -> 10 | P201: =IFERROR(_xlfn.XLOOKUP(K201,maestro_productos_15!$B$2:$B$16,maestro_productos_15!$C$2:$C$16),"No encontrada") -> Bazar | Q201: =IFERROR(_xlfn.XLOOKUP(K201,maestro_productos_15!$B$2:$B$16,maestro_productos_15!$D$2:$D$16),"No encontrada") -> Artesanías Guaraníes | R201: =ventas_raw_200[[#This Row],[Precio_Unitario]]*ventas_raw_200[[#This Row],[Cantidad_Auditada]] -> 85000 | S201: =ventas_raw_200[[#This Row],[Costo_Unitario]]*ventas_raw_200[[#This Row],[Cantidad_Auditada]] -> 48000 | T201: =ventas_raw_200[[#This Row],[Total_Venta]]-ventas_raw_200[[#This Row],[Total_Costo]] -> 37000 | U201: {=_xlfn.IFS(AND(G201>25000,I201="Corrientes"),O201*G201*0.06,G201>25000,O201*G201*0.04,TRUE,O201*G201*0.02)} -> 1700

Sheet maestro_productos_15
A1: SKU | B1: Producto | C1: Categoria | D1: Proveedor | E1: Precio_Lista | F1: Costo_Base
A2: SKU-101 | B2: Yerba Mate Premium 1kg | C2: Alimentos | D2: Cooperativa Neike | E2: 3800 | F2: 2500
A3: SKU-102 | B3: Alimento Perro Adulto 15kg | C3: Mascotas | D3: NutriDog Arg | E3: 35000 | F3: 24000
A4: SKU-103 | B4: Auriculares Bluetooth Pro | C4: Tecnología | D4: TechImport S.R.L. | E4: 28000 | F4: 18000
A5: SKU-104 | B5: Soporte Regulable Notebook | C5: Tecnología | D5: TechImport S.R.L. | E5: 19500 | F5: 12000
A6: SKU-105 | B6: Correa Reforzada Canina 3m | C6: Mascotas | D6: PetStyle Litoral | E6: 9200 | F6: 5500
A7: SKU-106 | B7: Juguete Mordillo Goma | C7: Mascotas | D7: PetStyle Litoral | E7: 4800 | F7: 2700
A8: SKU-107 | B8: Alimento Gato Castrado 10kg | C8: Mascotas | D8: NutriDog Arg | E8: 29500 | F8: 20000
A9: SKU-108 | B9: Teclado Mecánico RGB | C9: Tecnología | D9: TechImport S.R.L. | E9: 45000 | F9: 30000
A10: SKU-109 | B10: Café en Grano Intenso 1kg | C10: Alimentos | D10: Distribuidora del Nordeste | E10: 18500 | F10: 12500
A11: SKU-110 | B11: Mates de Madera Calada | C11: Bazar | D11: Artesanías Guaraníes | E11: 8500 | F11: 4800
A12: SKU-111 | B12: Termo Acero Inoxidable 1.3L | C12: Bazar | D12: Distribuidora del Nordeste | E12: 32000 | F12: 21000
A13: SKU-112 | B13: Mouse Inalámbrico Ergonómico | C13: Tecnología | D13: TechImport S.R.L. | E13: 15000 | F13: 9500
... A16: SKU-115 | B16: Cargador Rápido USB-C 65W | C16: Tecnología | D16: TechImport S.R.L. | E16: 22000 | F16: 14000

Sheet Reporte_consolidado
B4: Sucursal | C4: Facturación Total | F4: CATEGORÍA | G4: TOTAL VENTA | I4: CATEGORÍA | J4: TOTAL VENTA
B5: Corrientes | C5: {=SUM(_xlfn.IFS(ventas_raw_200!$I$2:$I$201=B5,ventas_raw_200!$O$2:$O$201*ventas_raw_200!$G$2:$G$201,TRUE,0))} -> 8339700 | F5: Alimentos | G5: 4607400 | I5: Corrientes | J5: 8339700
B6: Resistencia | C6: {=SUM(_xlfn.IFS(ventas_raw_200!$I$2:$I$201=B6,ventas_raw_200!$O$2:$O$201*ventas_raw_200!$G$2:$G$201,TRUE,0))} -> 13394400 | F6: Bazar | G6: 6317500 | I6: Formosa | J6: 6499100
B7: Posadas | C7: {=SUM(_xlfn.IFS(ventas_raw_200!$I$2:$I$201=B7,ventas_raw_200!$O$2:$O$201*ventas_raw_200!$G$2:$G$201,TRUE,0))} -> 12305400 | F7: Mascotas | G7: 9850700 | I7: Posadas | J7: 12305400
B8: Formosa | C8: {=SUM(_xlfn.IFS(ventas_raw_200!$I$2:$I$201=B8,ventas_raw_200!$O$2:$O$201*ventas_raw_200!$G$2:$G$201,TRUE,0))} -> 6499100 | F8: Tecnología | G8: 19763000 | I8: Resistencia | J8: 13394400

Sheet Dashboard_Ejecutivo
B3: Facturación Total General | C3: =SUM(Reporte_consolidado!C5:C8) -> 40538600
B4: Ganancia neta total (€) | C4: =SUM(ventas_raw_200[Ganancia]) -> 14226200
B5: Margen neto promedio | C5: =AVERAGE(C4/C3) -> 0.35092973

Sheet Dashboard_Alternativo CLaude
B1: Dashboard comercial alternativo · 1er trimestre 2026 | P1: CÁLCULOS AUXILIARES · no editar (alimentan filtros, ranking y gráficos)
B2: Fuente: tabla ventas_raw_200 (200 transacciones, 01/01–31/03/2026) + maestro_productos_15. Importes sin símbolo: las sucursales son argentinas y los precios encajan con ARS (el dashboard original los etiqueta en €). | P2: Lista sucursal | Q2: Lista mes
P3: Todas | Q3: Todos
B4: Filtro sucursal ▸ | C4: Todas | E4: Filtro mes ▸ | F4: Todos | H4: Celdas amarillas = desplegables. Cada bloque indica qué filtros le afectan. | P4: Corrientes | Q4: Enero
P5: Formosa | Q5: Febrero
B6: FACTURACIÓN | E6: MARGEN BRUTO (Ganancia) | H6: MARGEN BRUTO % | K6: COMISIONES | P6: Posadas | Q6: Marzo
B7: =SUMPRODUCT((($C$4="Todas")+(ventas_raw_200[Sucursal_limpio]=$C$4)>0)*(($Q$8=0)+(MONTH(ventas_raw_200[Fecha])=$Q$8)>0)*ventas_raw_200[Total_Venta]) -> 40538600 | E7: =SUMPRODUCT((($C$4="Todas")+(ventas_raw_200[Sucursal_limpio]=$C$4)>0)*(($Q$8=0)+(MONTH(ventas_raw_200[Fecha])=$Q$8)>0)*ventas_raw_200[Ganancia]) -> 14226200 | H7: =IFERROR(E7/B7,0) -> 0.35092973 | K7: =SUMPRODUCT((($C$4="Todas")+(ventas_raw_200[Sucursal_limpio]=$C$4)>0)*(($Q$8=0)+(MONTH(ventas_raw_200[Fecha])=$Q$8)>0)*ventas_raw_200[Comision]) -> 1392822 | P7: Resistencia
B8: % del total trimestre | D8: =IFERROR(B7/SUM(ventas_raw_200[Total_Venta]),0) -> 1 | E8: Antes de comisiones · % s/venta | G8: =IFERROR(E7/B7,0) -> 0.35092973 | H8: Media del trimestre (sin filtros) | J8: =SUM(ventas_raw_200[Ganancia])/SUM(ventas_raw_200[Total_Venta]) -> 0.35092973 | K8: % sobre facturación | M8: =IFERROR(K7/B7,0) -> 0.034357921 | P8: Nº de mes seleccionado (0 = todos) | Q8: =IFERROR(MATCH($F$4,$Q$4:$Q$6,0),0) -> 0
P9: Días del periodo seleccionado | Q9: =IF($Q$8=0,MAX(ventas_raw_200[Fecha])-MIN(ventas_raw_200[Fecha])+1,DAY(EOMONTH(DATE(YEAR(MIN(ventas_raw_200[Fecha])),$Q$8,1),0))) -> 90
B10: CONTRIBUCIÓN TRAS COMISIONES | E10: TRANSACCIONES | H10: TICKET MEDIO | K10: UNIDADES (auditadas)
B11: =E7-K7 -> 12833378 | E11: =SUMPRODUCT((($C$4="Todas")+(ventas_raw_200[Sucursal_limpio]=$C$4)>0)*(($Q$8=0)+(MONTH(ventas_raw_200[Fecha])=$Q$8)>0)) -> 200 | H11: =IFERROR(B7/E11,0) -> 202693 | K11: =SUMPRODUCT((($C$4="Todas")+(ventas_raw_200[Sucursal_limpio]=$C$4)>0)*(($Q$8=0)+(MONTH(ventas_raw_200[Fecha])=$Q$8)>0)*ventas_raw_200[Cantidad_Auditada]) -> 2288 | P11: Semana | Q11: Inicio (lunes) | R11: Fin | S11: Días con periodo | T11: Facturación | U11: Venta media / día | V11: Media móvil 3 semanas
B12: % sobre facturación | D12: =IFERROR(B11/B7,0) -> 0.31657181 | E12: Transacciones / día | G12: =IFERROR(E11/$Q$9,0) -> 2.2222222 | H12: Venta media / día | J12: =IFERROR(B7/$Q$9,0) -> 450428.89 | K12: Unidades / transacción | M12: =IFERROR(K11/E11,0) -> 11.44 | P12: S1 | Q12: =MIN(ventas_raw_200[Fecha])-WEEKDAY(MIN(ventas_raw_200[Fecha]),2)+1 -> 46020 | R12: =Q12+6 -> 46026 | S12: =MAX(0,MIN(R12,MAX(ventas_raw_200[Fecha]))-MAX(Q12,MIN(ventas_raw_200[Fecha]))+1) -> 4 | T12: =SUMPRODUCT((($C$4="Todas")+(ventas_raw_200[Sucursal_limpio]=$C$4)>0)*(ventas_raw_200[Fecha]>=Q12)*(ventas_raw_200[Fecha]<=R12)*ventas_raw_200[Total_Venta]) -> 3365800 | U12: =IFERROR(T12/S12,0) -> 841450 | V12: =IFERROR(SUM(T12:T12)/SUM(S12:S12),0) -> 841450
P13: S2 | Q13: =Q12+7 -> 46027 | R13: =Q13+6 -> 46033 | S13: =MAX(0,MIN(R13,MAX(ventas_raw_200[Fecha]))-MAX(Q13,MIN(ventas_raw_200[Fecha]))+1) -> 7 | T13: =SUMPRODUCT((($C$4="Todas")+(ventas_raw_200[Sucursal_limpio]=$C$4)>0)*(ventas_raw_200[Fecha]>=Q13)*(ventas_raw_200[Fecha]<=R13)*ventas_raw_200[Total_Venta]) -> 3718200 | U13: =IFERROR(T13/S13,0) -> 531171.43 | V13: =IFERROR(SUM(T12:T13)/SUM(S12:S13),0) -> 644000
B14: Hallazgos clave | P14: S3 | Q14: =Q13+7 -> 46034 | R14: =Q14+6 -> 46040 | S14: =MAX(0,MIN(R14,MAX(ventas_raw_200[Fecha]))-MAX(Q14,MIN(ventas_raw_200[Fecha]))+1) -> 7 | T14: =SUMPRODUCT((($C$4="Todas")+(ventas_raw_200[Sucursal_limpio]=$C$4)>0)*(ventas_raw_200[Fecha]>=Q14)*(ventas_raw_200[Fecha]<=R14)*ventas_raw_200[Total_Venta]) -> 2723600 | U14: =IFERROR(T14/S14,0) -> 389085.71 | V14: =IFERROR(SUM(T12:T14)/SUM(S12:S14),0) -> 544866.67
B15: Lectura del trimestre completo, sin filtros (texto fijo redactado a 24/10/2026; las cifras del resto del dashboard sí son fórmulas). | P15: S4 | Q15: =Q14+7 -> 46041 | R15: =Q15+6 -> 46047 | S15: =MAX(0,MIN(R15,MAX(ventas_raw_200[Fecha]))-MAX(Q15,MIN(ventas_raw_200[Fecha]))+1) -> 7 | T15: =SUMPRODUCT((($C$4="Todas")+(ventas_raw_200[Sucursal_limpio]=$C$4)>0)*(ventas_raw_200[Fecha]>=Q15)*(ventas_raw_200[Fecha]<=R15)*ventas_raw_200[Total_Venta]) -> 1437400 | U15: =IFERROR(T15/S15,0) -> 205342.86 | V15: =IFERROR(SUM(T13:T15)/SUM(S13:S15),0) -> 375200
B16: 1 · Concentración: Tecnología = 48,8 % de la facturación. 5 de 15 productos generan el 60 % y 9 productos el 87 % (ver Pareto ABC). | P16: S5 | Q16: =Q15+7 -> 46048 | R16: =Q16+6 -> 46054 | S16: =MAX(0,MIN(R16,MAX(ventas_raw_200[Fecha]))-MAX(Q16,MIN(ventas_raw_200[Fecha]))+1) -> 7 | T16: =SUMPRODUCT((($C$4="Todas")+(ventas_raw_200[Sucursal_limpio]=$C$4)>0)*(ventas_raw_200[Fecha]>=Q16)*(ventas_raw_200[Fecha]<=R16)*ventas_raw_200[Total_Venta]) -> 4710800 | U16: =IFERROR(T16/S16,0) -> 672971.43 | V16: =IFERROR(SUM(T14:T16)/SUM(S14:S16),0) -> 422466.67
B17: 2 · El esquema de comisiones premia el precio, no el margen: los productos con precio unitario > 25.000 son el 58,5 % de la venta con un margen del 33,7 % (vs 37,1 % del resto), pero se llevan el 76 % de las comisiones (4,5 % s/venta vs 2,0 %). | P17: S6 | Q17: =Q16+7 -> 46055 | R17: =Q17+6 -> 46061 | S17: =MAX(0,MIN(R17,MAX(ventas_raw_200[Fecha]))-MAX(Q17,MIN(ventas_raw_200[Fecha]))+1) -> 7 | T17: =SUMPRODUCT((($C$4="Todas")+(ventas_raw_200[Sucursal_limpio]=$C$4)>0)*(ventas_raw_200[Fecha]>=Q17)*(ventas_raw_200[Fecha]<=R17)*ventas_raw_200[Total_Venta]) -> 2730900 | U17: =IFERROR(T17/S17,0) -> 390128.57 | V17: =IFERROR(SUM(T15:T17)/SUM(S15:S17),0) -> 422814.29
B18: 3 · Los productos más rentables (Juguete Mordillo 43,8 %, Mates 43,5 %, Snack Perro 41,9 %) son los que menos facturan; el nº 1 en ventas (Teclado RGB, 33,3 %) es el de menor margen de Tecnología. | P18: S7 | Q18: =Q17+7 -> 46062 | R18: =Q18+6 -> 46068 | S18: =MAX(0,MIN(R18,MAX(ventas_raw_200[Fecha]))-MAX(Q18,MIN(ventas_raw_200[Fecha]))+1) -> 7 | T18: =SUMPRODUCT((($C$4="Todas")+(ventas_raw_200[Sucursal_limpio]=$C$4)>0)*(ventas_raw_200[Fecha]>=Q18)*(ventas_raw_200[Fecha]<=R18)*ventas_raw_200[Total_Venta]) -> 2230700 | U18: =IFERROR(T18/S18,0) -> 318671.43 | V18: =IFERROR(SUM(T16:T18)/SUM(S16:S18),0) -> 460590.48
B19: 4 · La venta media diaria cae de ≈472.500 (ene) a ≈419.100 (mar), −11 %, pero con 200 transacciones la semana oscila entre ≈171.000 y ≈829.000/día: señal a vigilar, no tendencia demostrada. Febrero: menos transacciones (52) y ticket medio más alto. | P19: S8 | Q19: =Q18+7 -> 46069 | R19: =Q19+6 -> 46075 | S19: =MAX(0,MIN(R19,MAX(ventas_raw_200[Fecha]))-MAX(Q19,MIN(ventas_raw_200[Fecha]))+1) -> 7 | T19: =SUMPRODUCT((($C$4="Todas")+(ventas_raw_200[Sucursal_limpio]=$C$4)>0)*(ventas_raw_200[Fecha]>=Q19)*(ventas_raw_200[Fecha]<=R19)*ventas_raw_200[Total_Venta]) -> 5803700 | U19: =IFERROR(T19/S19,0) -> 829100 | V19: =IFERROR(SUM(T17:T19)/SUM(S17:S19),0) -> 512633.33
B20: 5 · Formosa factura la mitad que Resistencia (6,5 M vs 13,4 M) y casi no vende Bazar. Corrientes paga 4,6 % de comisión s/venta frente a ≈3,1 % del resto por su tramo del 6 %. | P20: S9 | Q20: =Q19+7 -> 46076 | R20: =Q20+6 -> 46082 | S20: =MAX(0,MIN(R20,MAX(ventas_raw_200[Fecha]))-MAX(Q20,MIN(ventas_raw_200[Fecha]))+1) -> 7 | T20: =SUMPRODUCT((($C$4="Todas")+(ventas_raw_200[Sucursal_limpio]=$C$4)>0)*(ventas_raw_200[Fecha]>=Q20)*(ventas_raw_200[Fecha]<=R20)*ventas_raw_200[Total_Venta]) -> 1859700 | U20: =IFERROR(T20/S20,0) -> 265671.43 | V20: =IFERROR(SUM(T18:T20)/SUM(S18:S20),0) -> 471147.62
B21: 6 · Precio unitario = precio de lista en 200/200 ventas: no hay descuentos, así que el margen % solo se mueve por mix de producto. 194 de 200 registros tenían al menos un defecto de formato (ver Calidad de datos). | P21: S10 | Q21: =Q20+7 -> 46083 | R21: =Q21+6 -> 46089 | S21: =MAX(0,MIN(R21,MAX(ventas_raw_200[Fecha]))-MAX(Q21,MIN(ventas_raw_200[Fecha]))+1) -> 7 | T21: =SUMPRODUCT((($C$4="Todas")+(ventas_raw_200[Sucursal_limpio]=$C$4)>0)*(ventas_raw_200[Fecha]>=Q21)*(ventas_raw_200[Fecha]<=R21)*ventas_raw_200[Total_Venta]) -> 4787400 | U21: =IFERROR(T21/S21,0) -> 683914.29 | V21: =IFERROR(SUM(T19:T21)/SUM(S19:S21),0) -> 592895.24
P22: S11 | Q22: =Q21+7 -> 46090 | R22: =Q22+6 -> 46096 | S22: =MAX(0,MIN(R22,MAX(ventas_raw_200[Fecha]))-MAX(Q22,MIN(ventas_raw_200[Fecha]))+1) -> 7 | T22: =SUMPRODUCT((($C$4="Todas")+(ventas_raw_200[Sucursal_limpio]=$C$4)>0)*(ventas_raw_200[Fecha]>=Q22)*(ventas_raw_200[Fecha]<=R22)*ventas_raw_200[Total_Venta]) -> 1198400 | U22: =IFERROR(T22/S22,0) -> 171200 | V22: =IFERROR(SUM(T20:T22)/SUM(S20:S22),0) -> 373595.24
B23: 1 · Evolución temporal | P23: S12 | Q23: =Q22+7 -> 46097 | R23: =Q23+6 -> 46103 | S23: =MAX(0,MIN(R23,MAX(ventas_raw_200[Fecha]))-MAX(Q23,MIN(ventas_raw_200[Fecha]))+1) -> 7 | T23: =SUMPRODUCT((($C$4="Todas")+(ventas_raw_200[Sucursal_limpio]=$C$4)>0)*(ventas_raw_200[Fecha]>=Q23)*(ventas_raw_200[Fecha]<=R23)*ventas_raw_200[Total_Venta]) -> 2005000 | U23: =IFERROR(T23/S23,0) -> 286428.57 | V23: =IFERROR(SUM(T21:T23)/SUM(S21:S23),0) -> 380514.29
B24: Filtro aplicado: Sucursal. (El filtro de mes no aplica: este bloque compara meses.) | P24: S13 | Q24: =Q23+7 -> 46104 | R24: =Q24+6 -> 46110 | S24: =MAX(0,MIN(R24,MAX(ventas_raw_200[Fecha]))-MAX(Q24,MIN(ventas_raw_200[Fecha]))+1) -> 7 | T24: =SUMPRODUCT((($C$4="Todas")+(ventas_raw_200[Sucursal_limpio]=$C$4)>0)*(ventas_raw_200[Fecha]>=Q24)*(ventas_raw_200[Fecha]<=R24)*ventas_raw_200[Total_Venta]) -> 2598100 | U24: =IFERROR(T24/S24,0) -> 371157.14 | V24: =IFERROR(SUM(T22:T24)/SUM(S22:S24),0) -> 276261.9
B25: Mes | C25: Días | D25: Transacciones | E25: Facturación | F25: Δ % vs mes anterior | G25: Venta media / día | H25: Δ % venta / día | I25: Ticket medio | J25: Margen bruto % | P25: S14 | Q25: =Q24+7 -> 46111 | R25: =Q25+6 -> 46117 | S25: =MAX(0,MIN(R25,MAX(ventas_raw_200[Fecha]))-MAX(Q25,MIN(ventas_raw_200[Fecha]))+1) -> 2 | T25: =SUMPRODUCT((($C$4="Todas")+(ventas_raw_200[Sucursal_limpio]=$C$4)>0)*(ventas_raw_200[Fecha]>=Q25)*(ventas_raw_200[Fecha]<=R25)*ventas_raw_200[Total_Venta]) -> 1368900 | U25: =IFERROR(T25/S25,0) -> 684450 | V25: =IFERROR(SUM(T23:T25)/SUM(S23:S25),0) -> 373250
B26: Enero | C26: =DAY(EOMONTH(DATE(YEAR(MIN(ventas_raw_200[Fecha])),1,1),0)) -> 31 | D26: =SUMPRODUCT((($C$4="Todas")+(ventas_raw_200[Sucursal_limpio]=$C$4)>0)*(MONTH(ventas_raw_200[Fecha])=1)) -> 75 | E26: =SUMPRODUCT((($C$4="Todas")+(ventas_raw_200[Sucursal_limpio]=$C$4)>0)*(MONTH(ventas_raw_200[Fecha])=1)*ventas_raw_200[Total_Venta]) -> 14647800 | G26: =IFERROR(E26/C26,0) -> 472509.68 | I26: =IFERROR(E26/D26,0) -> 195304 | J26: =IFERROR(SUMPRODUCT((($C$4="Todas")+(ventas_raw_200[Sucursal_limpio]=$C$4)>0)*(MONTH(ventas_raw_200[Fecha])=1)*ventas_raw_200[Ganancia])/E26,0) -> 0.35025055
B27: Febrero | C27: =DAY(EOMONTH(DATE(YEAR(MIN(ventas_raw_200[Fecha])),2,1),0)) -> 28 | D27: =SUMPRODUCT((($C$4="Todas")+(ventas_raw_200[Sucursal_limpio]=$C$4)>0)*(MONTH(ventas_raw_200[Fecha])=2)) -> 52 | E27: =SUMPRODUCT((($C$4="Todas")+(ventas_raw_200[Sucursal_limpio]=$C$4)>0)*(MONTH(ventas_raw_200[Fecha])=2)*ventas_raw_200[Total_Venta]) -> 12898500 | F27: =IFERROR(E27/E26-1,0) -> -0.11942408 | G27: =IFERROR(E27/C27,0) -> 460660.71 | H27: =IFERROR(G27/G26-1,0) -> -0.025076657 | I27: =IFERROR(E27/D27,0) -> 248048.08 | J27: =IFERROR(SUMPRODUCT((($C$4="Todas")+(ventas_raw_200[Sucursal_limpio]=$C$4)>0)*(MONTH(ventas_raw_200[Fecha])=2)*ventas_raw_200[Ganancia])/E27,0) -> 0.35098655
B28: Marzo | C28: =DAY(EOMONTH(DATE(YEAR(MIN(ventas_raw_200[Fecha])),3,1),0)) -> 31 | D28: =SUMPRODUCT((($C$4="Todas")+(ventas_raw_200[Sucursal_limpio]=$C$4)>0)*(MONTH(ventas_raw_200[Fecha])=3)) -> 73 | E28: =SUMPRODUCT((($C$4="Todas")+(ventas_raw_200[Sucursal_limpio]=$C$4)>0)*(MONTH(ventas_raw_200[Fecha])=3)*ventas_raw_200[Total_Venta]) -> 12992300 | F28: =IFERROR(E28/E27-1,0) -> 0.0072721634 | G28: =IFERROR(E28/C28,0) -> 419106.45 | H28: =IFERROR(G28/G27-1,0) -> -0.090205788 | I28: =IFERROR(E28/D28,0) -> 177976.71 | J28: =IFERROR(SUMPRODUCT((($C$4="Todas")+(ventas_raw_200[Sucursal_limpio]=$C$4)>0)*(MONTH(ventas_raw_200[Fecha])=3)*ventas_raw_200[Ganancia])/E28,0) -> 0.35163905 | P28: Producto (maestro) | Q28: Categoría | R28: Precio lista | S28: Unidades | T28: Facturación | U28: Ganancia | V28: Clave orden | W28: Fila ranking
B29: Trimestre | C29: =SUM(C26:C28) -> 90 | D29: =SUM(D26:D28) -> 200 | E29: =SUM(E26:E28) -> 40538600 | G29: =IFERROR(E29/C29,0) -> 450428.89 | H29: =IFERROR(G28/G26-1,0) -> -0.11302039 | I29: =IFERROR(E29/D29,0) -> 202693 | J29: =IFERROR(SUMPRODUCT((($C$4="Todas")+(ventas_raw_200[Sucursal_limpio]=$C$4)>0)*ventas_raw_200[Ganancia])/E29,0) -> 0.35092973 | K29: ← Δ mar vs ene | P29: =maestro_productos_15!B2 -> Yerba Mate Premium 1kg | Q29: =maestro_productos_15!C2 -> Alimentos | R29: =maestro_productos_15!E2 -> 3800 | S29: =SUMPRODUCT((($C$4="Todas")+(ventas_raw_200[Sucursal_limpio]=$C$4)>0)*(($Q$8=0)+(MONTH(ventas_raw_200[Fecha])=$Q$8)>0)*(ventas_raw_200[Producto_limpio]=P29)*ventas_raw_200[Cantidad_Auditada]) -> 268 | T29: =SUMPRODUCT((($C$4="Todas")+(ventas_raw_200[Sucursal_limpio]=$C$4)>0)*(($Q$8=0)+(MONTH(ventas_raw_200[Fecha])=$Q$8)>0)*(ventas_raw_200[Producto_limpio]=P29)*ventas_raw_200[Total_Venta]) -> 1018400 | U29: =SUMPRODUCT((($C$4="Todas")+(ventas_raw_200[Sucursal_limpio]=$C$4)>0)*(($Q$8=0)+(MONTH(ventas_raw_200[Fecha])=$Q$8)>0)*(ventas_raw_200[Producto_limpio]=P29)*ventas_raw_200[Ganancia]) -> 348400 | V29: =T29+(100-ROW())/1000 -> 1018400.1
P30: =maestro_productos_15!B3 -> Alimento Perro Adulto 15kg | Q30: =maestro_productos_15!C3 -> Mascotas | R30: =maestro_productos_15!E3 -> 35000 | S30: =SUMPRODUCT((($C$4="Todas")+(ventas_raw_200[Sucursal_limpio]=$C$4)>0)*(($Q$8=0)+(MONTH(ventas_raw_200[Fecha])=$Q$8)>0)*(ventas_raw_200[Producto_limpio]=P30)*ventas_raw_200[Cantidad_Auditada]) -> 85 | T30: =SUMPRODUCT((($C$4="Todas")+(ventas_raw_200[Sucursal_limpio]=$C$4)>0)*(($Q$8=0)+(MONTH(ventas_raw_200[Fecha])=$Q$8)>0)*(ventas_raw_200[Producto_limpio]=P30)*ventas_raw_200[Total_Venta]) -> 2975000 | U30: =SUMPRODUCT((($C$4="Todas")+(ventas_raw_200[Sucursal_limpio]=$C$4)>0)*(($Q$8=0)+(MONTH(ventas_raw_200[Fecha])=$Q$8)>0)*(ventas_raw_200[Producto_limpio]=P30)*ventas_raw_200[Ganancia]) -> 935000 | V30: =T30+(100-ROW())/1000 -> 2975000.1
P31: =maestro_productos_15!B4 -> Auriculares Bluetooth Pro | Q31: =maestro_productos_15!C4 -> Tecnología | R31: =maestro_productos_15!E4 -> 28000 | S31: =SUMPRODUCT((($C$4="Todas")+(ventas_raw_200[Sucursal_limpio]=$C$4)>0)*(($Q$8=0)+(MONTH(ventas_raw_200[Fecha])=$Q$8)>0)*(ventas_raw_200[Producto_limpio]=P31)*ventas_raw_200[Cantidad_Auditada]) -> 192 | T31: =SUMPRODUCT((($C$4="Todas")+(ventas_raw_200[Sucursal_limpio]=$C$4)>0)*(($Q$8=0)+(MONTH(ventas_raw_200[Fecha])=$Q$8)>0)*(ventas_raw_200[Producto_limpio]=P31)*ventas_raw_200[Total_Venta]) -> 5376000 | U31: =SUMPRODUCT((($C$4="Todas")+(ventas_raw_200[Sucursal_limpio]=$C$4)>0)*(($Q$8=0)+(MONTH(ventas_raw_200[Fecha])=$Q$8)>0)*(ventas_raw_200[Producto_limpio]=P31)*ventas_raw_200[Ganancia]) -> 1920000 | V31: =T31+(100-ROW())/1000 -> 5376000.1
P32: =maestro_productos_15!B5 -> Soporte Regulable Notebook | Q32: =maestro_productos_15!C5 -> Tecnología | R32: =maestro_productos_15!E5 -> 19500 | S32: =SUMPRODUCT((($C$4="Todas")+(ventas_raw_200[Sucursal_limpio]=$C$4)>0)*(($Q$8=0)+(MONTH(ventas_raw_200[Fecha])=$Q$8)>0)*(ventas_raw_200[Producto_limpio]=P32)*ventas_raw_200[Cantidad_Auditada]) -> 146 | T32: =SUMPRODUCT((($C$4="Todas")+(ventas_raw_200[Sucursal_limpio]=$C$4)>0)*(($Q$8=0)+(MONTH(ventas_raw_200[Fecha])=$Q$8)>0)*(ventas_raw_200[Producto_limpio]=P32)*ventas_raw_200[Total_Venta]) -> 2847000 | U32: =SUMPRODUCT((($C$4="Todas")+(ventas_raw_200[Sucursal_limpio]=$C$4)>0)*(($Q$8=0)+(MONTH(ventas_raw_200[Fecha])=$Q$8)>0)*(ventas_raw_200[Producto_limpio]=P32)*ventas_raw_200[Ganancia]) -> 1095000 | V32: =T32+(100-ROW())/1000 -> 2847000.1
P33: =maestro_productos_15!B6 -> Correa Reforzada Canina 3m | Q33: =maestro_productos_15!C6 -> Mascotas | R33: =maestro_productos_15!E6 -> 9200 | S33: =SUMPRODUCT((($C$4="Todas")+(ventas_raw_200[Sucursal_limpio]=$C$4)>0)*(($Q$8=0)+(MONTH(ventas_raw_200[Fecha])=$Q$8)>0)*(ventas_raw_200[Producto_limpio]=P33)*ventas_raw_200[Cantidad_Auditada]) -> 138 | T33: =SUMPRODUCT((($C$4="Todas")+(ventas_raw_200[Sucursal_limpio]=$C$4)>0)*(($Q$8=0)+(MONTH(ventas_raw_200[Fecha])=$Q$8)>0)*(ventas_raw_200[Producto_limpio]=P33)*ventas_raw_200[Total_Venta]) -> 1269600 | U33: =SUMPRODUCT((($C$4="Todas")+(ventas_raw_200[Sucursal_limpio]=$C$4)>0)*(($Q$8=0)+(MONTH(ventas_raw_200[Fecha])=$Q$8)>0)*(ventas_raw_200[Producto_limpio]=P33)*ventas_raw_200[Ganancia]) -> 510600 | V33: =T33+(100-ROW())/1000 -> 1269600.1
P34: =maestro_productos_15!B7 -> Juguete Mordillo Goma | Q34: =maestro_productos_15!C7 -> Mascotas | R34: =maestro_productos_15!E7 -> 4800 | S34: =SUMPRODUCT((($C$4="Todas")+(ventas_raw_200[Sucursal_limpio]=$C$4)>0)*(($Q$8=0)+(MONTH(ventas_raw_200[Fecha])=$Q$8)>0)*(ventas_raw_200[Producto_limpio]=P34)*ventas_raw_200[Cantidad_Auditada]) -> 144 | T34: =SUMPRODUCT((($C$4="Todas")+(ventas_raw_200[Sucursal_limpio]=$C$4)>0)*(($Q$8=0)+(MONTH(ventas_raw_200[Fecha])=$Q$8)>0)*(ventas_raw_200[Producto_limpio]=P34)*ventas_raw_200[Total_Venta]) -> 691200 | U34: =SUMPRODUCT((($C$4="Todas")+(ventas_raw_200[Sucursal_limpio]=$C$4)>0)*(($Q$8=0)+(MONTH(ventas_raw_200[Fecha])=$Q$8)>0)*(ventas_raw_200[Producto_limpio]=P34)*ventas_raw_200[Ganancia]) -> 302400 | V34: =T34+(100-ROW())/1000 -> 691200.07
P35: =maestro_productos_15!B8 -> Alimento Gato Castrado 10kg | Q35: =maestro_productos_15!C8 -> Mascotas | R35: =maestro_productos_15!E8 -> 29500 | S35: =SUMPRODUCT((($C$4="Todas")+(ventas_raw_200[Sucursal_limpio]=$C$4)>0)*(($Q$8=0)+(MONTH(ventas_raw_200[Fecha])=$Q$8)>0)*(ventas_raw_200[Producto_limpio]=P35)*ventas_raw_200[Cantidad_Auditada]) -> 121 | T35: =SUMPRODUCT((($C$4="Todas")+(ventas_raw_200[Sucursal_limpio]=$C$4)>0)*(($Q$8=0)+(MONTH(ventas_raw_200[Fecha])=$Q$8)>0)*(ventas_raw_200[Producto_limpio]=P35)*ventas_raw_200[Total_Venta]) -> 3569500 | U35: =SUMPRODUCT((($C$4="Todas")+(ventas_raw_200[Sucursal_limpio]=$C$4)>0)*(($Q$8=0)+(MONTH(ventas_raw_200[Fecha])=$Q$8)>0)*(ventas_raw_200[Producto_limpio]=P35)*ventas_raw_200[Ganancia]) -> 1149500 | V35: =T35+(100-ROW())/1000 -> 3569500.1
P36: =maestro_productos_15!B9 -> Teclado Mecánico RGB | Q36: =maestro_productos_15!C9 -> Tecnología | R36: =maestro_productos_15!E9 -> 45000 | S36: =SUMPRODUCT((($C$4="Todas")+(ventas_raw_200[Sucursal_limpio]=$C$4)>0)*(($Q$8=0)+(MONTH(ventas_raw_200[Fecha])=$Q$8)>0)*(ventas_raw_200[Producto_limpio]=P36)*ventas_raw_200[Cantidad_Auditada]) -> 142 | T36: =SUMPRODUCT((($C$4="Todas")+(ventas_raw_200[Sucursal_limpio]=$C$4)>0)*(($Q$8=0)+(MONTH(ventas_raw_200[Fecha])=$Q$8)>0)*(ventas_raw_200[Producto_limpio]=P36)*ventas_raw_200[Total_Venta]) -> 6390000 | U36: =SUMPRODUCT((($C$4="Todas")+(ventas_raw_200[Sucursal_limpio]=$C$4)>0)*(($Q$8=0)+(MONTH(ventas_raw_200[Fecha])=$Q$8)>0)*(ventas_raw_200[Producto_limpio]=P36)*ventas_raw_200[Ganancia]) -> 2130000 | V36: =T36+(100-ROW())/1000 -> 6390000.1
P37: =maestro_productos_15!B10 -> Café en Grano Intenso 1kg | Q37: =maestro_productos_15!C10 -> Alimentos | R37: =maestro_productos_15!E10 -> 18500 | S37: =SUMPRODUCT((($C$4="Todas")+(ventas_raw_200[Sucursal_limpio]=$C$4)>0)*(($Q$8=0)+(MONTH(ventas_raw_200[Fecha])=$Q$8)>0)*(ventas_raw_200[Producto_limpio]=P37)*ventas_raw_200[Cantidad_Auditada]) -> 194 | T37: =SUMPRODUCT((($C$4="Todas")+(ventas_raw_200[Sucursal_limpio]=$C$4)>0)*(($Q$8=0)+(MONTH(ventas_raw_200[Fecha])=$Q$8)>0)*(ventas_raw_200[Producto_limpio]=P37)*ventas_raw_200[Total_Venta]) -> 3589000 | U37: =SUMPRODUCT((($C$4="Todas")+(ventas_raw_200[Sucursal_limpio]=$C$4)>0)*(($Q$8=0)+(MONTH(ventas_raw_200[Fecha])=$Q$8)>0)*(ventas_raw_200[Producto_limpio]=P37)*ventas_raw_200[Ganancia]) -> 1164000 | V37: =T37+(100-ROW())/1000 -> 3589000.1
P38: =maestro_productos_15!B11 -> Mates de Madera Calada | Q38: =maestro_productos_15!C11 -> Bazar | R38: =maestro_productos_15!E11 -> 8500 | S38: =SUMPRODUCT((($C$4="Todas")+(ventas_raw_200[Sucursal_limpio]=$C$4)>0)*(($Q$8=0)+(MONTH(ventas_raw_200[Fecha])=$Q$8)>0)*(ventas_raw_200[Producto_limpio]=P38)*ventas_raw_200[Cantidad_Auditada]) -> 107 | T38: =SUMPRODUCT((($C$4="Todas")+(ventas_raw_200[Sucursal_limpio]=$C$4)>0)*(($Q$8=0)+(MONTH(ventas_raw_200[Fecha])=$Q$8)>0)*(ventas_raw_200[Producto_limpio]=P38)*ventas_raw_200[Total_Venta]) -> 909500 | U38: =SUMPRODUCT((($C$4="Todas")+(ventas_raw_200[Sucursal_limpio]=$C$4)>0)*(($Q$8=0)+(MONTH(ventas_raw_200[Fecha])=$Q$8)>0)*(ventas_raw_200[Producto_limpio]=P38)*ventas_raw_200[Ganancia]) -> 395900 | V38: =T38+(100-ROW())/1000 -> 909500.06
P39: =maestro_productos_15!B12 -> Termo Acero Inoxidable 1.3L | Q39: =maestro_productos_15!C12 -> Bazar | R39: =maestro_productos_15!E12 -> 32000 | S39: =SUMPRODUCT((($C$4="Todas")+(ventas_raw_200[Sucursal_limpio]=$C$4)>0)*(($Q$8=0)+(MONTH(ventas_raw_200[Fecha])=$Q$8)>0)*(ventas_raw_200[Producto_limpio]=P39)*ventas_raw_200[Cantidad_Auditada]) -> 169 | T39: =SUMPRODUCT((($C$4="Todas")+(ventas_raw_200[Sucursal_limpio]=$C$4)>0)*(($Q$8=0)+(MONTH(ventas_raw_200[Fecha])=$Q$8)>0)*(ventas_raw_200[Producto_limpio]=P39)*ventas_raw_200[Total_Venta]) -> 5408000 | U39: =SUMPRODUCT((($C$4="Todas")+(ventas_raw_200[Sucursal_limpio]=$C$4)>0)*(($Q$8=0)+(MONTH(ventas_raw_200[Fecha])=$Q$8)>0)*(ventas_raw_200[Producto_limpio]=P39)*ventas_raw_200[Ganancia]) -> 1859000 | V39: =T39+(100-ROW())/1000 -> 5408000.1
P40: =maestro_productos_15!B13 -> Mouse Inalámbrico Ergonómico | Q40: =maestro_productos_15!C13 -> Tecnología | R40: =maestro_productos_15!E13 -> 15000 | S40: =SUMPRODUCT((($C$4="Todas")+(ventas_raw_200[Sucursal_limpio]=$C$4)>0)*(($Q$8=0)+(MONTH(ventas_raw_200[Fecha])=$Q$8)>0)*(ventas_raw_200[Producto_limpio]=P40)*ventas_raw_200[Cantidad_Auditada]) -> 182 | T40: =SUMPRODUCT((($C$4="Todas")+(ventas_raw_200[Sucursal_limpio]=$C$4)>0)*(($Q$8=0)+(MONTH(ventas_raw_200[Fecha])=$Q$8)>0)*(ventas_raw_200[Producto_limpio]=P40)*ventas_raw_200[Total_Venta]) -> 2730000 | U40: =SUMPRODUCT((($C$4="Todas")+(ventas_raw_200[Sucursal_limpio]=$C$4)>0)*(($Q$8=0)+(MONTH(ventas_raw_200[Fecha])=$Q$8)>0)*(ventas_raw_200[Producto_limpio]=P40)*ventas_raw_200[Ganancia]) -> 1001000 | V40: =T40+(100-ROW())/1000 -> 2730000.1
P41: =maestro_productos_15!B14 -> Shampoo Canino Neutro 500ml | Q41: =maestro_productos_15!C14 -> Mascotas | R41: =maestro_productos_15!E14 -> 6200 | S41: =SUMPRODUCT((($C$4="Todas")+(ventas_raw_200[Sucursal_limpio]=$C$4)>0)*(($Q$8=0)+(MONTH(ventas_raw_200[Fecha])=$Q$8)>0)*(ventas_raw_200[Producto_limpio]=P41)*ventas_raw_200[Cantidad_Auditada]) -> 144 | T41: =SUMPRODUCT((($C$4="Todas")+(ventas_raw_200[Sucursal_limpio]=$C$4)>0)*(($Q$8=0)+(MONTH(ventas_raw_200[Fecha])=$Q$8)>0)*(ventas_raw_200[Producto_limpio]=P41)*ventas_raw_200[Total_Venta]) -> 892800 | U41: =SUMPRODUCT((($C$4="Todas")+(ventas_raw_200[Sucursal_limpio]=$C$4)>0)*(($Q$8=0)+(MONTH(ventas_raw_200[Fecha])=$Q$8)>0)*(ventas_raw_200[Producto_limpio]=P41)*ventas_raw_200[Ganancia]) -> 345600 | V41: =T41+(100-ROW())/1000 -> 892800.06
... P43: =maestro_productos_15!B16 -> Cargador Rápido USB-C 65W | Q43: =maestro_productos_15!C16 -> Tecnología | R43: =maestro_productos_15!E16 -> 22000 | S43: =SUMPRODUCT((($C$4="Todas")+(ventas_raw_200[Sucursal_limpio]=$C$4)>0)*(($Q$8=0)+(MONTH(ventas_raw_200[Fecha])=$Q$8)>0)*(ventas_raw_200[Producto_limpio]=P43)*ventas_raw_200[Cantidad_Auditada]) -> 110 | T43: =SUMPRODUCT((($C$4="Todas")+(ventas_raw_200[Sucursal_limpio]=$C$4)>0)*(($Q$8=0)+(MONTH(ventas_raw_200[Fecha])=$Q$8)>0)*(ventas_raw_200[Producto_limpio]=P43)*ventas_raw_200[Total_Venta]) -> 2420000 | U43: =SUMPRODUCT((($C$4="Todas")+(ventas_raw_200[Sucursal_limpio]=$C$4)>0)*(($Q$8=0)+(MONTH(ventas_raw_200[Fecha])=$Q$8)>0)*(ventas_raw_200[Producto_limpio]=P43)*ventas_raw_200[Ganancia]) -> 880000 | V43: =T43+(100-ROW())/1000 -> 2420000.1
B47: 2 · Sucursal × Categoría (mapa de calor de facturación)
B48: Filtro aplicado: Mes. Intensidad de color = facturación de la celda.
B49: Sucursal | C49: Alimentos | D49: Bazar | E49: Mascotas | F49: Tecnología | G49: Total | H49: % s/total | I49: Margen bruto % | J49: Comisión % s/venta | K49: Contribución %
B50: Corrientes | C50: =SUMPRODUCT((($Q$8=0)+(MONTH(ventas_raw_200[Fecha])=$Q$8)>0)*(ventas_raw_200[Sucursal_limpio]=$B50)*(ventas_raw_200[Categoria_oficial]=C$49)*ventas_raw_200[Total_Venta]) -> 546600 | D50: =SUMPRODUCT((($Q$8=0)+(MONTH(ventas_raw_200[Fecha])=$Q$8)>0)*(ventas_raw_200[Sucursal_limpio]=$B50)*(ventas_raw_200[Categoria_oficial]=D$49)*ventas_raw_200[Total_Venta]) -> 1959000 | E50: =SUMPRODUCT((($Q$8=0)+(MONTH(ventas_raw_200[Fecha])=$Q$8)>0)*(ventas_raw_200[Sucursal_limpio]=$B50)*(ventas_raw_200[Categoria_oficial]=E$49)*ventas_raw_200[Total_Venta]) -> 1675600 | F50: =SUMPRODUCT((($Q$8=0)+(MONTH(ventas_raw_200[Fecha])=$Q$8)>0)*(ventas_raw_200[Sucursal_limpio]=$B50)*(ventas_raw_200[Categoria_oficial]=F$49)*ventas_raw_200[Total_Venta]) -> 4158500 | G50: =SUM(C50:F50) -> 8339700 | H50: =IFERROR(G50/G$54,0) -> 0.20572245 | I50: =IFERROR(SUMPRODUCT((($Q$8=0)+(MONTH(ventas_raw_200[Fecha])=$Q$8)>0)*(ventas_raw_200[Sucursal_limpio]=$B50)*ventas_raw_200[Ganancia])/G50,0) -> 0.35207501 | J50: =IFERROR(SUMPRODUCT((($Q$8=0)+(MONTH(ventas_raw_200[Fecha])=$Q$8)>0)*(ventas_raw_200[Sucursal_limpio]=$B50)*ventas_raw_200[Comision])/G50,0) -> 0.045823471 | K50: =IFERROR((SUMPRODUCT((($Q$8=0)+(MONTH(ventas_raw_200[Fecha])=$Q$8)>0)*(ventas_raw_200[Sucursal_limpio]=$B50)*ventas_raw_200[Ganancia])-SUMPRODUCT((($Q$8=0)+(MONTH(ventas_raw_200[Fecha])=$Q$8)>0)*(ventas_raw_200[Sucursal_limpio]=$B50)*ventas_raw_200[Comision]))/G50,0) -> 0.30625154
B51: Formosa | C51: =SUMPRODUCT((($Q$8=0)+(MONTH(ventas_raw_200[Fecha])=$Q$8)>0)*(ventas_raw_200[Sucursal_limpio]=$B51)*(ventas_raw_200[Categoria_oficial]=C$49)*ventas_raw_200[Total_Venta]) -> 1218400 | D51: =SUMPRODUCT((($Q$8=0)+(MONTH(ventas_raw_200[Fecha])=$Q$8)>0)*(ventas_raw_200[Sucursal_limpio]=$B51)*(ventas_raw_200[Categoria_oficial]=D$49)*ventas_raw_200[Total_Venta]) -> 160000 | E51: =SUMPRODUCT((($Q$8=0)+(MONTH(ventas_raw_200[Fecha])=$Q$8)>0)*(ventas_raw_200[Sucursal_limpio]=$B51)*(ventas_raw_200[Categoria_oficial]=E$49)*ventas_raw_200[Total_Venta]) -> 2471200 | F51: =SUMPRODUCT((($Q$8=0)+(MONTH(ventas_raw_200[Fecha])=$Q$8)>0)*(ventas_raw_200[Sucursal_limpio]=$B51)*(ventas_raw_200[Categoria_oficial]=F$49)*ventas_raw_200[Total_Venta]) -> 2649500 | G51: =SUM(C51:F51) -> 6499100 | H51: =IFERROR(G51/G$54,0) -> 0.16031881 | I51: =IFERROR(SUMPRODUCT((($Q$8=0)+(MONTH(ventas_raw_200[Fecha])=$Q$8)>0)*(ventas_raw_200[Sucursal_limpio]=$B51)*ventas_raw_200[Ganancia])/G51,0) -> 0.34557093 | J51: =IFERROR(SUMPRODUCT((($Q$8=0)+(MONTH(ventas_raw_200[Fecha])=$Q$8)>0)*(ventas_raw_200[Sucursal_limpio]=$B51)*ventas_raw_200[Comision])/G51,0) -> 0.031429275 | K51: =IFERROR((SUMPRODUCT((($Q$8=0)+(MONTH(ventas_raw_200[Fecha])=$Q$8)>0)*(ventas_raw_200[Sucursal_limpio]=$B51)*ventas_raw_200[Ganancia])-SUMPRODUCT((($Q$8=0)+(MONTH(ventas_raw_200[Fecha])=$Q$8)>0)*(ventas_raw_200[Sucursal_limpio]=$B51)*ventas_raw_200[Comision]))/G51,0) -> 0.31414165
B52: Posadas | C52: =SUMPRODUCT((($Q$8=0)+(MONTH(ventas_raw_200[Fecha])=$Q$8)>0)*(ventas_raw_200[Sucursal_limpio]=$B52)*(ventas_raw_200[Categoria_oficial]=C$49)*ventas_raw_200[Total_Venta]) -> 1139500 | D52: =SUMPRODUCT((($Q$8=0)+(MONTH(ventas_raw_200[Fecha])=$Q$8)>0)*(ventas_raw_200[Sucursal_limpio]=$B52)*(ventas_raw_200[Categoria_oficial]=D$49)*ventas_raw_200[Total_Venta]) -> 1076000 | E52: =SUMPRODUCT((($Q$8=0)+(MONTH(ventas_raw_200[Fecha])=$Q$8)>0)*(ventas_raw_200[Sucursal_limpio]=$B52)*(ventas_raw_200[Categoria_oficial]=E$49)*ventas_raw_200[Total_Venta]) -> 3137400 | F52: =SUMPRODUCT((($Q$8=0)+(MONTH(ventas_raw_200[Fecha])=$Q$8)>0)*(ventas_raw_200[Sucursal_limpio]=$B52)*(ventas_raw_200[Categoria_oficial]=F$49)*ventas_raw_200[Total_Venta]) -> 6952500 | G52: =SUM(C52:F52) -> 12305400 | H52: =IFERROR(G52/G$54,0) -> 0.30354773 | I52: =IFERROR(SUMPRODUCT((($Q$8=0)+(MONTH(ventas_raw_200[Fecha])=$Q$8)>0)*(ventas_raw_200[Sucursal_limpio]=$B52)*ventas_raw_200[Ganancia])/G52,0) -> 0.35496611 | J52: =IFERROR(SUMPRODUCT((($Q$8=0)+(MONTH(ventas_raw_200[Fecha])=$Q$8)>0)*(ventas_raw_200[Sucursal_limpio]=$B52)*ventas_raw_200[Comision])/G52,0) -> 0.030412502 | K52: =IFERROR((SUMPRODUCT((($Q$8=0)+(MONTH(ventas_raw_200[Fecha])=$Q$8)>0)*(ventas_raw_200[Sucursal_limpio]=$B52)*ventas_raw_200[Ganancia])-SUMPRODUCT((($Q$8=0)+(MONTH(ventas_raw_200[Fecha])=$Q$8)>0)*(ventas_raw_200[Sucursal_limpio]=$B52)*ventas_raw_200[Comision]))/G52,0) -> 0.32455361
B53: Resistencia | C53: =SUMPRODUCT((($Q$8=0)+(MONTH(ventas_raw_200[Fecha])=$Q$8)>0)*(ventas_raw_200[Sucursal_limpio]=$B53)*(ventas_raw_200[Categoria_oficial]=C$49)*ventas_raw_200[Total_Venta]) -> 1702900 | D53: =SUMPRODUCT((($Q$8=0)+(MONTH(ventas_raw_200[Fecha])=$Q$8)>0)*(ventas_raw_200[Sucursal_limpio]=$B53)*(ventas_raw_200[Categoria_oficial]=D$49)*ventas_raw_200[Total_Venta]) -> 3122500 | E53: =SUMPRODUCT((($Q$8=0)+(MONTH(ventas_raw_200[Fecha])=$Q$8)>0)*(ventas_raw_200[Sucursal_limpio]=$B53)*(ventas_raw_200[Categoria_oficial]=E$49)*ventas_raw_200[Total_Venta]) -> 2566500 | F53: =SUMPRODUCT((($Q$8=0)+(MONTH(ventas_raw_200[Fecha])=$Q$8)>0)*(ventas_raw_200[Sucursal_limpio]=$B53)*(ventas_raw_200[Categoria_oficial]=F$49)*ventas_raw_200[Total_Venta]) -> 6002500 | G53: =SUM(C53:F53) -> 13394400 | H53: =IFERROR(G53/G$54,0) -> 0.33041102 | I53: =IFERROR(SUMPRODUCT((($Q$8=0)+(MONTH(ventas_raw_200[Fecha])=$Q$8)>0)*(ventas_raw_200[Sucursal_limpio]=$B53)*ventas_raw_200[Ganancia])/G53,0) -> 0.34910858 | J53: =IFERROR(SUMPRODUCT((($Q$8=0)+(MONTH(ventas_raw_200[Fecha])=$Q$8)>0)*(ventas_raw_200[Sucursal_limpio]=$B53)*ventas_raw_200[Comision])/G53,0) -> 0.032264827 | K53: =IFERROR((SUMPRODUCT((($Q$8=0)+(MONTH(ventas_raw_200[Fecha])=$Q$8)>0)*(ventas_raw_200[Sucursal_limpio]=$B53)*ventas_raw_200[Ganancia])-SUMPRODUCT((($Q$8=0)+(MONTH(ventas_raw_200[Fecha])=$Q$8)>0)*(ventas_raw_200[Sucursal_limpio]=$B53)*ventas_raw_200[Comision]))/G53,0) -> 0.31684376
B54: Total | C54: =SUM(C50:C53) -> 4607400 | D54: =SUM(D50:D53) -> 6317500 | E54: =SUM(E50:E53) -> 9850700 | F54: =SUM(F50:F53) -> 19763000 | G54: =SUM(G50:G53) -> 40538600 | H54: =IFERROR(G54/G54,0) -> 1 | I54: =IFERROR(SUMPRODUCT((($Q$8=0)+(MONTH(ventas_raw_200[Fecha])=$Q$8)>0)*ventas_raw_200[Ganancia])/G54,0) -> 0.35092973 | J54: =IFERROR(SUMPRODUCT((($Q$8=0)+(MONTH(ventas_raw_200[Fecha])=$Q$8)>0)*ventas_raw_200[Comision])/G54,0) -> 0.034357921 | K54: =IFERROR((SUMPRODUCT((($Q$8=0)+(MONTH(ventas_raw_200[Fecha])=$Q$8)>0)*ventas_raw_200[Ganancia])-SUMPRODUCT((($Q$8=0)+(MONTH(ventas_raw_200[Fecha])=$Q$8)>0)*ventas_raw_200[Comision]))/G54,0) -> 0.31657181
B55: % s/total | C55: =IFERROR(C54/$G$54,0) -> 0.11365464 | D55: =IFERROR(D54/$G$54,0) -> 0.15583913 | E55: =IFERROR(E54/$G$54,0) -> 0.24299556 | F55: =IFERROR(F54/$G$54,0) -> 0.48751067
B56: Margen bruto % | C56: =IFERROR(SUMPRODUCT((($Q$8=0)+(MONTH(ventas_raw_200[Fecha])=$Q$8)>0)*(ventas_raw_200[Categoria_oficial]=C$49)*ventas_raw_200[Ganancia])/C54,0) -> 0.32825455 | D56: =IFERROR(SUMPRODUCT((($Q$8=0)+(MONTH(ventas_raw_200[Fecha])=$Q$8)>0)*(ventas_raw_200[Categoria_oficial]=D$49)*ventas_raw_200[Ganancia])/D54,0) -> 0.35692917 | E56: =IFERROR(SUMPRODUCT((($Q$8=0)+(MONTH(ventas_raw_200[Fecha])=$Q$8)>0)*(ventas_raw_200[Categoria_oficial]=E$49)*ventas_raw_200[Ganancia])/E54,0) -> 0.348493 | F56: =IFERROR(SUMPRODUCT((($Q$8=0)+(MONTH(ventas_raw_200[Fecha])=$Q$8)>0)*(ventas_raw_200[Categoria_oficial]=F$49)*ventas_raw_200[Ganancia])/F54,0) -> 0.35551283
B59: 3 · Vendedores
B60: Filtros aplicados: Sucursal y Mes. Barras = facturación relativa.
B61: Vendedor | C61: Transacciones | D61: Unidades | E61: Facturación | F61: % s/total | G61: Ticket medio | H61: Margen bruto % | I61: Comisión | J61: Comisión % s/venta | K61: Contribución %
B62: Ana Martinez | C62: =SUMPRODUCT((($C$4="Todas")+(ventas_raw_200[Sucursal_limpio]=$C$4)>0)*(($Q$8=0)+(MONTH(ventas_raw_200[Fecha])=$Q$8)>0)*(ventas_raw_200[Vendedor_limpio]=$B62)) -> 69 | D62: =SUMPRODUCT((($C$4="Todas")+(ventas_raw_200[Sucursal_limpio]=$C$4)>0)*(($Q$8=0)+(MONTH(ventas_raw_200[Fecha])=$Q$8)>0)*(ventas_raw_200[Vendedor_limpio]=$B62)*ventas_raw_200[Cantidad_Auditada]) -> 777 | E62: =SUMPRODUCT((($C$4="Todas")+(ventas_raw_200[Sucursal_limpio]=$C$4)>0)*(($Q$8=0)+(MONTH(ventas_raw_200[Fecha])=$Q$8)>0)*(ventas_raw_200[Vendedor_limpio]=$B62)*ventas_raw_200[Total_Venta]) -> 13768300 | F62: =IFERROR(E62/E$66,0) -> 0.33963432 | G62: =IFERROR(E62/C62,0) -> 199540.58 | H62: =IFERROR(SUMPRODUCT((($C$4="Todas")+(ventas_raw_200[Sucursal_limpio]=$C$4)>0)*(($Q$8=0)+(MONTH(ventas_raw_200[Fecha])=$Q$8)>0)*(ventas_raw_200[Vendedor_limpio]=$B62)*ventas_raw_200[Ganancia])/E62,0) -> 0.34686199 | I62: =SUMPRODUCT((($C$4="Todas")+(ventas_raw_200[Sucursal_limpio]=$C$4)>0)*(($Q$8=0)+(MONTH(ventas_raw_200[Fecha])=$Q$8)>0)*(ventas_raw_200[Vendedor_limpio]=$B62)*ventas_raw_200[Comision]) -> 453536 | J62: =IFERROR(I62/E62,0) -> 0.032940595 | K62: =IFERROR((SUMPRODUCT((($C$4="Todas")+(ventas_raw_200[Sucursal_limpio]=$C$4)>0)*(($Q$8=0)+(MONTH(ventas_raw_200[Fecha])=$Q$8)>0)*(ventas_raw_200[Vendedor_limpio]=$B62)*ventas_raw_200[Ganancia])-I62)/E62,0) -> 0.3139214
B63: Carlos Ruiz | C63: =SUMPRODUCT((($C$4="Todas")+(ventas_raw_200[Sucursal_limpio]=$C$4)>0)*(($Q$8=0)+(MONTH(ventas_raw_200[Fecha])=$Q$8)>0)*(ventas_raw_200[Vendedor_limpio]=$B63)) -> 62 | D63: =SUMPRODUCT((($C$4="Todas")+(ventas_raw_200[Sucursal_limpio]=$C$4)>0)*(($Q$8=0)+(MONTH(ventas_raw_200[Fecha])=$Q$8)>0)*(ventas_raw_200[Vendedor_limpio]=$B63)*ventas_raw_200[Cantidad_Auditada]) -> 766 | E63: =SUMPRODUCT((($C$4="Todas")+(ventas_raw_200[Sucursal_limpio]=$C$4)>0)*(($Q$8=0)+(MONTH(ventas_raw_200[Fecha])=$Q$8)>0)*(ventas_raw_200[Vendedor_limpio]=$B63)*ventas_raw_200[Total_Venta]) -> 12850300 | F63: =IFERROR(E63/E$66,0) -> 0.31698924 | G63: =IFERROR(E63/C63,0) -> 207262.9 | H63: =IFERROR(SUMPRODUCT((($C$4="Todas")+(ventas_raw_200[Sucursal_limpio]=$C$4)>0)*(($Q$8=0)+(MONTH(ventas_raw_200[Fecha])=$Q$8)>0)*(ventas_raw_200[Vendedor_limpio]=$B63)*ventas_raw_200[Ganancia])/E63,0) -> 0.35674654 | I63: =SUMPRODUCT((($C$4="Todas")+(ventas_raw_200[Sucursal_limpio]=$C$4)>0)*(($Q$8=0)+(MONTH(ventas_raw_200[Fecha])=$Q$8)>0)*(ventas_raw_200[Vendedor_limpio]=$B63)*ventas_raw_200[Comision]) -> 433686 | J63: =IFERROR(I63/E63,0) -> 0.033749095 | K63: =IFERROR((SUMPRODUCT((($C$4="Todas")+(ventas_raw_200[Sucursal_limpio]=$C$4)>0)*(($Q$8=0)+(MONTH(ventas_raw_200[Fecha])=$Q$8)>0)*(ventas_raw_200[Vendedor_limpio]=$B63)*ventas_raw_200[Ganancia])-I63)/E63,0) -> 0.32299744
B64: Juan Perez | C64: =SUMPRODUCT((($C$4="Todas")+(ventas_raw_200[Sucursal_limpio]=$C$4)>0)*(($Q$8=0)+(MONTH(ventas_raw_200[Fecha])=$Q$8)>0)*(ventas_raw_200[Vendedor_limpio]=$B64)) -> 50 | D64: =SUMPRODUCT((($C$4="Todas")+(ventas_raw_200[Sucursal_limpio]=$C$4)>0)*(($Q$8=0)+(MONTH(ventas_raw_200[Fecha])=$Q$8)>0)*(ventas_raw_200[Vendedor_limpio]=$B64)*ventas_raw_200[Cantidad_Auditada]) -> 536 | E64: =SUMPRODUCT((($C$4="Todas")+(ventas_raw_200[Sucursal_limpio]=$C$4)>0)*(($Q$8=0)+(MONTH(ventas_raw_200[Fecha])=$Q$8)>0)*(ventas_raw_200[Vendedor_limpio]=$B64)*ventas_raw_200[Total_Venta]) -> 9631300 | F64: =IFERROR(E64/E$66,0) -> 0.23758344 | G64: =IFERROR(E64/C64,0) -> 192626 | H64: =IFERROR(SUMPRODUCT((($C$4="Todas")+(ventas_raw_200[Sucursal_limpio]=$C$4)>0)*(($Q$8=0)+(MONTH(ventas_raw_200[Fecha])=$Q$8)>0)*(ventas_raw_200[Vendedor_limpio]=$B64)*ventas_raw_200[Ganancia])/E64,0) -> 0.35038884 | I64: =SUMPRODUCT((($C$4="Todas")+(ventas_raw_200[Sucursal_limpio]=$C$4)>0)*(($Q$8=0)+(MONTH(ventas_raw_200[Fecha])=$Q$8)>0)*(ventas_raw_200[Vendedor_limpio]=$B64)*ventas_raw_200[Comision]) -> 351526 | J64: =IFERROR(I64/E64,0) -> 0.036498292 | K64: =IFERROR((SUMPRODUCT((($C$4="Todas")+(ventas_raw_200[Sucursal_limpio]=$C$4)>0)*(($Q$8=0)+(MONTH(ventas_raw_200[Fecha])=$Q$8)>0)*(ventas_raw_200[Vendedor_limpio]=$B64)*ventas_raw_200[Ganancia])-I64)/E64,0) -> 0.31389054
B65: Maria Gomez | C65: =SUMPRODUCT((($C$4="Todas")+(ventas_raw_200[Sucursal_limpio]=$C$4)>0)*(($Q$8=0)+(MONTH(ventas_raw_200[Fecha])=$Q$8)>0)*(ventas_raw_200[Vendedor_limpio]=$B65)) -> 19 | D65: =SUMPRODUCT((($C$4="Todas")+(ventas_raw_200[Sucursal_limpio]=$C$4)>0)*(($Q$8=0)+(MONTH(ventas_raw_200[Fecha])=$Q$8)>0)*(ventas_raw_200[Vendedor_limpio]=$B65)*ventas_raw_200[Cantidad_Auditada]) -> 209 | E65: =SUMPRODUCT((($C$4="Todas")+(ventas_raw_200[Sucursal_limpio]=$C$4)>0)*(($Q$8=0)+(MONTH(ventas_raw_200[Fecha])=$Q$8)>0)*(ventas_raw_200[Vendedor_limpio]=$B65)*ventas_raw_200[Total_Venta]) -> 4288700 | F65: =IFERROR(E65/E$66,0) -> 0.105793 | G65: =IFERROR(E65/C65,0) -> 225721.05 | H65: =IFERROR(SUMPRODUCT((($C$4="Todas")+(ventas_raw_200[Sucursal_limpio]=$C$4)>0)*(($Q$8=0)+(MONTH(ventas_raw_200[Fecha])=$Q$8)>0)*(ventas_raw_200[Vendedor_limpio]=$B65)*ventas_raw_200[Ganancia])/E65,0) -> 0.34777438 | I65: =SUMPRODUCT((($C$4="Todas")+(ventas_raw_200[Sucursal_limpio]=$C$4)>0)*(($Q$8=0)+(MONTH(ventas_raw_200[Fecha])=$Q$8)>0)*(ventas_raw_200[Vendedor_limpio]=$B65)*ventas_raw_200[Comision]) -> 154074 | J65: =IFERROR(I65/E65,0) -> 0.035925572 | K65: =IFERROR((SUMPRODUCT((($C$4="Todas")+(ventas_raw_200[Sucursal_limpio]=$C$4)>0)*(($Q$8=0)+(MONTH(ventas_raw_200[Fecha])=$Q$8)>0)*(ventas_raw_200[Vendedor_limpio]=$B65)*ventas_raw_200[Ganancia])-I65)/E65,0) -> 0.31184881
B66: Total | C66: =SUM(C62:C65) -> 200 | D66: =SUM(D62:D65) -> 2288 | E66: =SUM(E62:E65) -> 40538600 | F66: =IFERROR(E66/E66,0) -> 1 | G66: =IFERROR(E66/C66,0) -> 202693 | H66: =IFERROR($E$7/E66,0) -> 0.35092973 | I66: =SUM(I62:I65) -> 1392822 | J66: =IFERROR(I66/E66,0) -> 0.034357921 | K66: =IFERROR(($E$7-I66)/E66,0) -> 0.31657181
B69: 4 · Productos · ranking y Pareto ABC
B70: Filtros aplicados: Sucursal y Mes. Ordenado por facturación. Clase A = productos que acumulan hasta el umbral A; B hasta umbral B; resto C. | K70: Umbral A | L70: 0.8 | M70: 0.95
B71: Producto | C71: Categoría | D71: Unidades | E71: Facturación | F71: % s/total | G71: % acumulado | H71: Clase ABC | I71: Margen bruto % | J71: Precio lista | K71: Tramo comisión | L71: Nº
B72: =INDEX($P$29:$P$43,$W72) -> Teclado Mecánico RGB | C72: =INDEX($Q$29:$Q$43,$W72) -> Tecnología | D72: =INDEX($S$29:$S$43,$W72) -> 142 | E72: =INDEX($T$29:$T$43,$W72) -> 6390000 | F72: =IFERROR(E72/SUM($E$72:$E$86),0) -> 0.15762755 | G72: =F72 -> 0.15762755 | H72: =IF(E72=0,"—",IF(G72-F72<$L$70,"A",IF(G72-F72<$M$70,"B","C"))) -> A | I72: =IFERROR(INDEX($U$29:$U$43,$W72)/E72,0) -> 0.33333333 | J72: =INDEX($R$29:$R$43,$W72) -> 45000 | K72: =IF(J72>$C$128,"Alto (4–6 %)","Base (2 %)") -> Alto (4–6 %) | L72: 1 | W72: =MATCH(LARGE($V$29:$V$43,1),$V$29:$V$43,0) -> 8
B73: =INDEX($P$29:$P$43,$W73) -> Termo Acero Inoxidable 1.3L | C73: =INDEX($Q$29:$Q$43,$W73) -> Bazar | D73: =INDEX($S$29:$S$43,$W73) -> 169 | E73: =INDEX($T$29:$T$43,$W73) -> 5408000 | F73: =IFERROR(E73/SUM($E$72:$E$86),0) -> 0.13340372 | G73: =G72+F73 -> 0.29103126 | H73: =IF(E73=0,"—",IF(G73-F73<$L$70,"A",IF(G73-F73<$M$70,"B","C"))) -> A | I73: =IFERROR(INDEX($U$29:$U$43,$W73)/E73,0) -> 0.34375 | J73: =INDEX($R$29:$R$43,$W73) -> 32000 | K73: =IF(J73>$C$128,"Alto (4–6 %)","Base (2 %)") -> Alto (4–6 %) | L73: 2 | W73: =MATCH(LARGE($V$29:$V$43,2),$V$29:$V$43,0) -> 11
B74: =INDEX($P$29:$P$43,$W74) -> Auriculares Bluetooth Pro | C74: =INDEX($Q$29:$Q$43,$W74) -> Tecnología | D74: =INDEX($S$29:$S$43,$W74) -> 192 | E74: =INDEX($T$29:$T$43,$W74) -> 5376000 | F74: =IFERROR(E74/SUM($E$72:$E$86),0) -> 0.13261435 | G74: =G73+F74 -> 0.42364561 | H74: =IF(E74=0,"—",IF(G74-F74<$L$70,"A",IF(G74-F74<$M$70,"B","C"))) -> A | I74: =IFERROR(INDEX($U$29:$U$43,$W74)/E74,0) -> 0.35714286 | J74: =INDEX($R$29:$R$43,$W74) -> 28000 | K74: =IF(J74>$C$128,"Alto (4–6 %)","Base (2 %)") -> Alto (4–6 %) | L74: 3 | W74: =MATCH(LARGE($V$29:$V$43,3),$V$29:$V$43,0) -> 3
B75: =INDEX($P$29:$P$43,$W75) -> Café en Grano Intenso 1kg | C75: =INDEX($Q$29:$Q$43,$W75) -> Alimentos | D75: =INDEX($S$29:$S$43,$W75) -> 194 | E75: =INDEX($T$29:$T$43,$W75) -> 3589000 | F75: =IFERROR(E75/SUM($E$72:$E$86),0) -> 0.088532904 | G75: =G74+F75 -> 0.51217852 | H75: =IF(E75=0,"—",IF(G75-F75<$L$70,"A",IF(G75-F75<$M$70,"B","C"))) -> A | I75: =IFERROR(INDEX($U$29:$U$43,$W75)/E75,0) -> 0.32432432 | J75: =INDEX($R$29:$R$43,$W75) -> 18500 | K75: =IF(J75>$C$128,"Alto (4–6 %)","Base (2 %)") -> Base (2 %) | L75: 4 | W75: =MATCH(LARGE($V$29:$V$43,4),$V$29:$V$43,0) -> 9
B76: =INDEX($P$29:$P$43,$W76) -> Alimento Gato Castrado 10kg | C76: =INDEX($Q$29:$Q$43,$W76) -> Mascotas | D76: =INDEX($S$29:$S$43,$W76) -> 121 | E76: =INDEX($T$29:$T$43,$W76) -> 3569500 | F76: =IFERROR(E76/SUM($E$72:$E$86),0) -> 0.088051881 | G76: =G75+F76 -> 0.6002304 | H76: =IF(E76=0,"—",IF(G76-F76<$L$70,"A",IF(G76-F76<$M$70,"B","C"))) -> A | I76: =IFERROR(INDEX($U$29:$U$43,$W76)/E76,0) -> 0.3220339 | J76: =INDEX($R$29:$R$43,$W76) -> 29500 | K76: =IF(J76>$C$128,"Alto (4–6 %)","Base (2 %)") -> Alto (4–6 %) | L76: 5 | W76: =MATCH(LARGE($V$29:$V$43,5),$V$29:$V$43,0) -> 7
B77: =INDEX($P$29:$P$43,$W77) -> Alimento Perro Adulto 15kg | C77: =INDEX($Q$29:$Q$43,$W77) -> Mascotas | D77: =INDEX($S$29:$S$43,$W77) -> 85 | E77: =INDEX($T$29:$T$43,$W77) -> 2975000 | F77: =IFERROR(E77/SUM($E$72:$E$86),0) -> 0.073386846 | G77: =G76+F77 -> 0.67361724 | H77: =IF(E77=0,"—",IF(G77-F77<$L$70,"A",IF(G77-F77<$M$70,"B","C"))) -> A | I77: =IFERROR(INDEX($U$29:$U$43,$W77)/E77,0) -> 0.31428571 | J77: =INDEX($R$29:$R$43,$W77) -> 35000 | K77: =IF(J77>$C$128,"Alto (4–6 %)","Base (2 %)") -> Alto (4–6 %) | L77: 6 | W77: =MATCH(LARGE($V$29:$V$43,6),$V$29:$V$43,0) -> 2
B78: =INDEX($P$29:$P$43,$W78) -> Soporte Regulable Notebook | C78: =INDEX($Q$29:$Q$43,$W78) -> Tecnología | D78: =INDEX($S$29:$S$43,$W78) -> 146 | E78: =INDEX($T$29:$T$43,$W78) -> 2847000 | F78: =IFERROR(E78/SUM($E$72:$E$86),0) -> 0.070229362 | G78: =G77+F78 -> 0.74384661 | H78: =IF(E78=0,"—",IF(G78-F78<$L$70,"A",IF(G78-F78<$M$70,"B","C"))) -> A | I78: =IFERROR(INDEX($U$29:$U$43,$W78)/E78,0) -> 0.38461538 | J78: =INDEX($R$29:$R$43,$W78) -> 19500 | K78: =IF(J78>$C$128,"Alto (4–6 %)","Base (2 %)") -> Base (2 %) | L78: 7 | W78: =MATCH(LARGE($V$29:$V$43,7),$V$29:$V$43,0) -> 4
B79: =INDEX($P$29:$P$43,$W79) -> Mouse Inalámbrico Ergonómico | C79: =INDEX($Q$29:$Q$43,$W79) -> Tecnología | D79: =INDEX($S$29:$S$43,$W79) -> 182 | E79: =INDEX($T$29:$T$43,$W79) -> 2730000 | F79: =IFERROR(E79/SUM($E$72:$E$86),0) -> 0.067343223 | G79: =G78+F79 -> 0.81118983 | H79: =IF(E79=0,"—",IF(G79-F79<$L$70,"A",IF(G79-F79<$M$70,"B","C"))) -> A | I79: =IFERROR(INDEX($U$29:$U$43,$W79)/E79,0) -> 0.36666667 | J79: =INDEX($R$29:$R$43,$W79) -> 15000 | K79: =IF(J79>$C$128,"Alto (4–6 %)","Base (2 %)") -> Base (2 %) | L79: 8 | W79: =MATCH(LARGE($V$29:$V$43,8),$V$29:$V$43,0) -> 12
B80: =INDEX($P$29:$P$43,$W80) -> Cargador Rápido USB-C 65W | C80: =INDEX($Q$29:$Q$43,$W80) -> Tecnología | D80: =INDEX($S$29:$S$43,$W80) -> 110 | E80: =INDEX($T$29:$T$43,$W80) -> 2420000 | F80: =IFERROR(E80/SUM($E$72:$E$86),0) -> 0.059696191 | G80: =G79+F80 -> 0.87088602 | H80: =IF(E80=0,"—",IF(G80-F80<$L$70,"A",IF(G80-F80<$M$70,"B","C"))) -> B | I80: =IFERROR(INDEX($U$29:$U$43,$W80)/E80,0) -> 0.36363636 | J80: =INDEX($R$29:$R$43,$W80) -> 22000 | K80: =IF(J80>$C$128,"Alto (4–6 %)","Base (2 %)") -> Base (2 %) | L80: 9 | W80: =MATCH(LARGE($V$29:$V$43,9),$V$29:$V$43,0) -> 15
B81: =INDEX($P$29:$P$43,$W81) -> Correa Reforzada Canina 3m | C81: =INDEX($Q$29:$Q$43,$W81) -> Mascotas | D81: =INDEX($S$29:$S$43,$W81) -> 138 | E81: =INDEX($T$29:$T$43,$W81) -> 1269600 | F81: =IFERROR(E81/SUM($E$72:$E$86),0) -> 0.031318299 | G81: =G80+F81 -> 0.90220432 | H81: =IF(E81=0,"—",IF(G81-F81<$L$70,"A",IF(G81-F81<$M$70,"B","C"))) -> B | I81: =IFERROR(INDEX($U$29:$U$43,$W81)/E81,0) -> 0.40217391 | J81: =INDEX($R$29:$R$43,$W81) -> 9200 | K81: =IF(J81>$C$128,"Alto (4–6 %)","Base (2 %)") -> Base (2 %) | L81: 10 | W81: =MATCH(LARGE($V$29:$V$43,10),$V$29:$V$43,0) -> 5
B82: =INDEX($P$29:$P$43,$W82) -> Yerba Mate Premium 1kg | C82: =INDEX($Q$29:$Q$43,$W82) -> Alimentos | D82: =INDEX($S$29:$S$43,$W82) -> 268 | E82: =INDEX($T$29:$T$43,$W82) -> 1018400 | F82: =IFERROR(E82/SUM($E$72:$E$86),0) -> 0.025121736 | G82: =G81+F82 -> 0.92732605 | H82: =IF(E82=0,"—",IF(G82-F82<$L$70,"A",IF(G82-F82<$M$70,"B","C"))) -> B | I82: =IFERROR(INDEX($U$29:$U$43,$W82)/E82,0) -> 0.34210526 | J82: =INDEX($R$29:$R$43,$W82) -> 3800 | K82: =IF(J82>$C$128,"Alto (4–6 %)","Base (2 %)") -> Base (2 %) | L82: 11 | W82: =MATCH(LARGE($V$29:$V$43,11),$V$29:$V$43,0) -> 1
B83: =INDEX($P$29:$P$43,$W83) -> Mates de Madera Calada | C83: =INDEX($Q$29:$Q$43,$W83) -> Bazar | D83: =INDEX($S$29:$S$43,$W83) -> 107 | E83: =INDEX($T$29:$T$43,$W83) -> 909500 | F83: =IFERROR(E83/SUM($E$72:$E$86),0) -> 0.022435407 | G83: =G82+F83 -> 0.94976146 | H83: =IF(E83=0,"—",IF(G83-F83<$L$70,"A",IF(G83-F83<$M$70,"B","C"))) -> B | I83: =IFERROR(INDEX($U$29:$U$43,$W83)/E83,0) -> 0.43529412 | J83: =INDEX($R$29:$R$43,$W83) -> 8500 | K83: =IF(J83>$C$128,"Alto (4–6 %)","Base (2 %)") -> Base (2 %) | L83: 12 | W83: =MATCH(LARGE($V$29:$V$43,12),$V$29:$V$43,0) -> 10
B84: =INDEX($P$29:$P$43,$W84) -> Shampoo Canino Neutro 500ml | C84: =INDEX($Q$29:$Q$43,$W84) -> Mascotas | D84: =INDEX($S$29:$S$43,$W84) -> 144 | E84: =INDEX($T$29:$T$43,$W84) -> 892800 | F84: =IFERROR(E84/SUM($E$72:$E$86),0) -> 0.022023454 | G84: =G83+F84 -> 0.97178492 | H84: =IF(E84=0,"—",IF(G84-F84<$L$70,"A",IF(G84-F84<$M$70,"B","C"))) -> B | I84: =IFERROR(INDEX($U$29:$U$43,$W84)/E84,0) -> 0.38709677 | J84: =INDEX($R$29:$R$43,$W84) -> 6200 | K84: =IF(J84>$C$128,"Alto (4–6 %)","Base (2 %)") -> Base (2 %) | L84: 13 | W84: =MATCH(LARGE($V$29:$V$43,13),$V$29:$V$43,0) -> 13
B85: =INDEX($P$29:$P$43,$W85) -> Juguete Mordillo Goma | C85: =INDEX($Q$29:$Q$43,$W85) -> Mascotas | D85: =INDEX($S$29:$S$43,$W85) -> 144 | E85: =INDEX($T$29:$T$43,$W85) -> 691200 | F85: =IFERROR(E85/SUM($E$72:$E$86),0) -> 0.017050416 | G85: =G84+F85 -> 0.98883533 | H85: =IF(E85=0,"—",IF(G85-F85<$L$70,"A",IF(G85-F85<$M$70,"B","C"))) -> C | I85: =IFERROR(INDEX($U$29:$U$43,$W85)/E85,0) -> 0.4375 | J85: =INDEX($R$29:$R$43,$W85) -> 4800 | K85: =IF(J85>$C$128,"Alto (4–6 %)","Base (2 %)") -> Base (2 %) | L85: 14 | W85: =MATCH(LARGE($V$29:$V$43,14),$V$29:$V$43,0) -> 6
B86: =INDEX($P$29:$P$43,$W86) -> Snack Premios Perro 250g | C86: =INDEX($Q$29:$Q$43,$W86) -> Mascotas | D86: =INDEX($S$29:$S$43,$W86) -> 146 | E86: =INDEX($T$29:$T$43,$W86) -> 452600 | F86: =IFERROR(E86/SUM($E$72:$E$86),0) -> 0.011164668 | G86: =G85+F86 -> 1 | H86: =IF(E86=0,"—",IF(G86-F86<$L$70,"A",IF(G86-F86<$M$70,"B","C"))) -> C | I86: =IFERROR(INDEX($U$29:$U$43,$W86)/E86,0) -> 0.41935484 | J86: =INDEX($R$29:$R$43,$W86) -> 3100 | K86: =IF(J86>$C$128,"Alto (4–6 %)","Base (2 %)") -> Base (2 %) | L86: 15 | W86: =MATCH(LARGE($V$29:$V$43,15),$V$29:$V$43,0) -> 14
B110: 5 · Calidad de datos (auditoría de la tabla bruta)
B111: Sin filtros. Mide lo que la limpieza de columnas *_limpio / Cantidad_Auditada ha tenido que corregir.
B112: Control | C112: Registros | D112: % s/total | E112: Estado | F112: Impacto en facturación | G112: Comentario
B113: Sucursal con espacios / mayúsculas | C113: =SUMPRODUCT(1-EXACT(ventas_raw_200[Sucursal],ventas_raw_200[Sucursal_limpio])) -> 109 | D113: =IFERROR(C113/ROWS(ventas_raw_200[ID_Transaccion]),0) -> 0.545 | E113: =IF(C113=0,"OK","Revisar") -> Revisar | F113: — | G113: Corregido con PROPER(TRIM()). 7 variantes de texto → 4 sucursales.
B114: Vendedor con espacios / mayúsculas | C114: =SUMPRODUCT(1-EXACT(ventas_raw_200[Vendedor],ventas_raw_200[Vendedor_limpio])) -> 114 | D114: =IFERROR(C114/ROWS(ventas_raw_200[ID_Transaccion]),0) -> 0.57 | E114: =IF(C114=0,"OK","Revisar") -> Revisar | F114: — | G114: 7 variantes → 4 vendedores.
B115: Producto con espacios / mayúsculas | C115: =SUMPRODUCT(1-EXACT(ventas_raw_200[Producto],ventas_raw_200[Producto_limpio])) -> 146 | D115: =IFERROR(C115/ROWS(ventas_raw_200[ID_Transaccion]),0) -> 0.73 | E115: =IF(C115=0,"OK","Revisar") -> Revisar | F115: — | G115: 40 variantes → 15 productos. Ojo: PROPER deja '1Kg', '500Ml' (cosmético; el cruce funciona porque no distingue mayúsculas).
B116: ID de transacción con espacios | C116: =SUMPRODUCT(--(ventas_raw_200[Largo_ID]<>ventas_raw_200[Largo_ID2])) -> 25 | D116: =IFERROR(C116/ROWS(ventas_raw_200[ID_Transaccion]),0) -> 0.125 | E116: =IF(C116=0,"OK","Revisar") -> Revisar | F116: — | G116: Corregido con TRIM().
B117: ID duplicado (tras limpieza) | C117: =ROWS(ventas_raw_200[ID_Transaccion])-SUMPRODUCT(1/COUNTIF(ventas_raw_200[ID_Transaccion_Limpio],ventas_raw_200[ID_Transaccion_Limpio])) -> 0 | D117: =IFERROR(C117/ROWS(ventas_raw_200[ID_Transaccion]),0) -> 0 | E117: =IF(C117=0,"OK","Revisar") -> OK | F117: — | G117: La clave de transacción debe ser única.
B118: Cantidad negativa (imputada como 1) | C118: =COUNTIF(ventas_raw_200[Cantidad],"<0") -> 3 | D118: =IFERROR(C118/ROWS(ventas_raw_200[ID_Transaccion]),0) -> 0.015 | E118: =IF(C118=0,"OK","Revisar") -> Revisar | F118: =SUMPRODUCT((ventas_raw_200[Cantidad]<0)*ventas_raw_200[Total_Venta]) -> 34200 | G118: Decisión discutible: −5 parece una devolución. Imputar 1 suma esta venta; tratarlo como devolución restaría además 5 uds × precio.
B119: Producto sin cruce con el maestro | C119: =COUNTIF(ventas_raw_200[Categoria_oficial],"No encontrada") -> 0 | D119: =IFERROR(C119/ROWS(ventas_raw_200[ID_Transaccion]),0) -> 0 | E119: =IF(C119=0,"OK","Revisar") -> OK | F119: — | G119: Cruce con XLOOKUP sobre el maestro (no distingue mayúsculas).
B120: Precio unitario ≠ precio de lista | C120: =SUMPRODUCT(--(ventas_raw_200[Precio_Unitario]<>SUMIFS(maestro_productos_15[Precio_Lista],maestro_productos_15[Producto],ventas_raw_200[Producto_limpio]))) -> 0 | D120: =IFERROR(C120/ROWS(ventas_raw_200[ID_Transaccion]),0) -> 0 | E120: =IF(C120=0,"OK","Revisar") -> OK | F120: — | G120: No hay descuentos: el margen % de cada producto es fijo.
B121: Coste unitario ≠ coste base | C121: =SUMPRODUCT(--(ventas_raw_200[Costo_Unitario]<>SUMIFS(maestro_productos_15[Costo_Base],maestro_productos_15[Producto],ventas_raw_200[Producto_limpio]))) -> 0 | D121: =IFERROR(C121/ROWS(ventas_raw_200[ID_Transaccion]),0) -> 0 | E121: =IF(C121=0,"OK","Revisar") -> OK | F121: — | G121: Si es 0, el margen viene íntegramente del maestro.
B122: Registros con ≥ 1 incidencia | C122: =SUMPRODUCT(--(((1-EXACT(ventas_raw_200[Sucursal],ventas_raw_200[Sucursal_limpio]))+(1-EXACT(ventas_raw_200[Vendedor],ventas_raw_200[Vendedor_limpio]))+(1-EXACT(ventas_raw_200[Producto],ventas_raw_200[Producto_limpio]))+(ventas_raw_200[Largo_ID]<>ventas_raw_200[Largo_ID2])+(ventas_raw_200[Cantidad]<0))>0)) -> 194 | D122: =IFERROR(C122/ROWS(ventas_raw_200[ID_Transaccion]),0) -> 0.97 | E122: =IF(C122=0,"OK","Revisar") -> Revisar | F122: — | G122: El origen necesita validación en la captura, no solo limpieza posterior.
B125: 6 · Simulador de comisiones (what-if)
B126: Sin filtros. Cambia las celdas amarillas (texto azul). Con los valores por defecto el esquema actual debe cuadrar con la columna Comision.
B127: Parámetros | C127: Valor | E127: Resultado | G127: Esquema actual (parámetros) | H127: Alternativo (% s/margen) | I127: Diferencia
B128: Umbral de precio unitario | C128: 25000 | E128: Comisión total | G128: =SUMPRODUCT(ventas_raw_200[Cantidad_Auditada]*ventas_raw_200[Precio_Unitario]*($C$129+(ventas_raw_200[Precio_Unitario]>$C$128)*($C$130-$C$129)+(ventas_raw_200[Precio_Unitario]>$C$128)*(ventas_raw_200[Sucursal_limpio]="Corrientes")*($C$131-$C$130))) -> 1392822 | H128: =$C$132*SUM(ventas_raw_200[Ganancia]) -> 1422620 | I128: =H128-G128 -> 29798
B129: Tasa base | C129: 0.02 | E129: Comisión % s/facturación | G129: =IFERROR(G128/SUM(ventas_raw_200[Total_Venta]),0) -> 0.034357921 | H129: =IFERROR(H128/SUM(ventas_raw_200[Total_Venta]),0) -> 0.035092973 | I129: =H129-G129 -> 0.00073505252
B130: Tasa precio alto | C130: 0.04 | E130: Contribución tras comisiones | G130: =SUM(ventas_raw_200[Ganancia])-G128 -> 12833378 | H130: =SUM(ventas_raw_200[Ganancia])-H128 -> 12803580 | I130: =H130-G130 -> -29798
B131: Tasa precio alto en Corrientes | C131: 0.06 | E131: % de la comisión en productos de precio alto | G131: =IFERROR(SUMPRODUCT((ventas_raw_200[Precio_Unitario]>$C$128)*ventas_raw_200[Cantidad_Auditada]*ventas_raw_200[Precio_Unitario]*($C$129+(ventas_raw_200[Precio_Unitario]>$C$128)*($C$130-$C$129)+(ventas_raw_200[Precio_Unitario]>$C$128)*(ventas_raw_200[Sucursal_limpio]="Corrientes")*($C$131-$C$130)))/G128,0) -> 0.75847452 | H131: =IFERROR(SUMPRODUCT((ventas_raw_200[Precio_Unitario]>$C$128)*ventas_raw_200[Ganancia])/SUM(ventas_raw_200[Ganancia]),0) -> 0.56188582 | I131: =H131-G131 -> -0.19658871
B132: Alternativa: % sobre margen bruto | C132: 0.1 | E132: Control: comisión actual en la tabla | G132: =SUM(ventas_raw_200[Comision]) -> 1392822 | H132: =IF(ABS(G128-G132)<1,"✓ cuadra con los parámetros por defecto","Parámetros modificados: difiere de la tabla") -> ✓ cuadra con los parámetros por defecto
B133: Supuestos tomados de la fórmula de la columna Comision (tramos del 2 / 4 / 6 %). La tasa alternativa es una propuesta para comparar.
...

Sheet Chart Data
A1: Categoría oficial | B1: Ventas (€)
A2: Tecnología | B2: {=SUMPRODUCT((ventas_raw_200[Categoria_oficial]=A2)*ventas_raw_200[Cantidad_Auditada]*ventas_raw_200[Precio_Unitario])} -> 19763000
A3: Mascotas | B3: {=SUMPRODUCT((ventas_raw_200[Categoria_oficial]=A3)*ventas_raw_200[Cantidad_Auditada]*ventas_raw_200[Precio_Unitario])} -> 9850700
A4: Bazar | B4: {=SUMPRODUCT((ventas_raw_200[Categoria_oficial]=A4)*ventas_raw_200[Cantidad_Auditada]*ventas_raw_200[Precio_Unitario])} -> 6317500
A5: Alimentos | B5: {=SUMPRODUCT((ventas_raw_200[Categoria_oficial]=A5)*ventas_raw_200[Cantidad_Auditada]*ventas_raw_200[Precio_Unitario])} -> 4607400
